Workbook

Sheet B.D.
A5: TIPO DE COMPRA | C5: TIPO DE GASTOS | E5: T / P | G5: DEL MES | I5: PAGADO O POR PAGAR
A6: REPOSICION DE MERCANCIA | C6: ACTIVOS | E6: BANCOS | G6: SI | I6: PAGADO
A7: PAGO 25% IVA | C7: AGUA | E7: EFECTIVO | G7: NO | I7: POR PAGAR
C8: ALIMENTOS/ REFRIGERIOS | E8: MONEDA EXTRANJERA
C9: ALQUILERES | E9: CAJA ADMON
C10: ASEO URBANO
C11: AYUDA SOCIAL DE TRANSPORTE
C12: BANAVIH
C13: BONO ALIMENTACION
C14: CAFÉ AZUCAR OTROS
C15: CANTV
C16: CARNETS
C17: COMISIONES BANCARIAS
C18: COMPLEMENTO BONO ALIMENTACION
C19: DIGITEL
C20: DELIVERYS EN COMPRAS
C21: DONACIÓN
... C72: VACACIONES

Sheet RESUMEN
A2: GLOBAL IT SYSTEM, C.A.
A3: RESULTADO ($$)
A4: DEL 01 AL 31 DE JULIO DE 2026
A6: INGRESOS
A7: BASE IMPONIBLE | B7: =+INGRESOS!P30 -> 319720.24 | C7: =+B7+B8 -> 370875.48
A8: IVA | B8: =+B7*0.16 -> 51155.239
A9: NE | B9: =+INGRESOS!S30 -> 204068.08 | C9: =+INGRESOS!S30 -> 204068.08
A10: IGTF | C10: =+INGRESOS!E31 -> 584.10166
A11: TOTAL VENTAS | E11: =+C7+C9+C10 -> 575527.66
A13: COMPRAS
A14: {=+'B.D.'!$A$6:$A$7} -> REPOSICION DE MERCANCIA | B14: =+IFERROR(VLOOKUP(A14,'T.D COMPRAS'!$A$1:B10,2,0),0) -> 227987.17
A15: PAGO 25% IVA | B15: =+IFERROR(VLOOKUP(A15,'T.D COMPRAS'!$A$1:B11,2,0),0) -> 10524.504
C16: =SUM(B14:B15) -> 238511.68
A18: TOTAL COMPRAS | E18: =+C16 -> 238511.68
A20: UTILIDAD BRUTA | E20: =+E11-E18 -> 337015.99
A22: GASTOS
A23: AGUA | B23: =+IFERROR(VLOOKUP(A23,'T.D GASTOS'!$A$5:B47,2,0),0) -> 0
A24: BONO ALIMENTACION | B24: =+IFERROR(VLOOKUP(A24,'T.D GASTOS'!$A$5:B48,2,0),0) -> 1518.7244
A25: COMPLEMENTO BONO ALIMENTACION | B25: =+IFERROR(VLOOKUP(A25,'T.D GASTOS'!$A$5:B49,2,0),0) -> 4563.0579
A26: NOMINA | B26: =+IFERROR(VLOOKUP(A26,'T.D GASTOS'!$A$5:B50,2,0),0) -> 406.77021
A27: AYUDA SOCIAL DE TRANSPORTE | B27: =+IFERROR(VLOOKUP(A27,'T.D GASTOS'!$A$5:B51,2,0),0) -> 3136.7156
A28: OTROS PERSONAL | B28: =+IFERROR(VLOOKUP(A28,'T.D GASTOS'!$A$5:B52,2,0),0) -> 0
A29: UNIFORMES | B29: =+IFERROR(VLOOKUP(A29,'T.D GASTOS'!$A$5:B53,2,0),0) -> 0
A30: UTILIDADES | B30: =+IFERROR(VLOOKUP(A30,'T.D GASTOS'!$A$5:B37,2,0),0) -> 0
A31: VACACIONES | B31: =+IFERROR(VLOOKUP(A31,'T.D GASTOS'!$A$5:B38,2,0),0) -> 0
C32: =SUM(B22:B32) -> 9625.2681
A34: AGUA | B34: =+IFERROR(VLOOKUP(A34,'T.D GASTOS'!$A$5:B41,2,0),0) -> 0
A35: ALIMENTOS/ REFRIGERIOS | B35: =+IFERROR(VLOOKUP(A35,'T.D GASTOS'!$A$5:B42,2,0),0) -> 0
A36: ALQUILERES | B36: =+IFERROR(VLOOKUP(A36,'T.D GASTOS'!$A$5:B43,2,0),0) -> 2289.2339
A37: ASEO URBANO | B37: =+IFERROR(VLOOKUP(A37,'T.D GASTOS'!$A$5:B44,2,0),0) -> 28.313278
A38: CAFÉ AZUCAR OTROS | B38: =+IFERROR(VLOOKUP(A38,'T.D GASTOS'!$A$5:B44,2,0),0) -> 330.89989
A39: CANTV | B39: =+IFERROR(VLOOKUP(A39,'T.D GASTOS'!$A$5:B45,2,0),0) -> 31.978726
A40: DIGITEL | B40: =+IFERROR(VLOOKUP(A40,'T.D GASTOS'!$A$5:B46,2,0),0) -> 125.60974
A41: DELIVERYS EN COMPRAS | B41: =+IFERROR(VLOOKUP(A41,'T.D GASTOS'!$A$5:B47,2,0),0) -> 0
A42: COMISIONES BANCARIAS | B42: =+IFERROR(VLOOKUP(A42,'T.D GASTOS'!$A$5:B48,2,0),0) -> 0
A43: ELECTRICIDAD | B43: =+IFERROR(VLOOKUP(A43,'T.D GASTOS'!$A$5:B49,2,0),0) -> 318.49488
A44: GASOLINA | B44: =+IFERROR(VLOOKUP(A44,'T.D GASTOS'!$A$5:B50,2,0),0) -> 42.687377
A45: GASTOS DE ALMACEN | B45: =+IFERROR(VLOOKUP(A45,'T.D GASTOS'!$A$5:B51,2,0),0) -> 0
A46: GASTOS BANCARIOS | B46: =+IFERROR(VLOOKUP(A46,'T.D GASTOS'!$A$5:B52,2,0),0) -> 0
A47: GASTOS OPERATIVOS | B47: =+IFERROR(VLOOKUP(A47,'T.D GASTOS'!$A$5:B53,2,0),0) -> 43.154994
A48: HIDROCAPITAL | B48: =+IFERROR(VLOOKUP(A48,'T.D GASTOS'!$A$5:B53,2,0),0) -> 104.61625
A49: HONORARIOS PROFESIONALES | B49: =+IFERROR(VLOOKUP(A49,'T.D GASTOS'!$A$5:B54,2,0),0) -> 1802.5876
A50: IMPRENTA | B50: =+IFERROR(VLOOKUP(A50,'T.D GASTOS'!$A$5:B55,2,0),0) -> 0
A51: INTERNET | B51: =+IFERROR(VLOOKUP(A51,'T.D GASTOS'!$A$5:B56,2,0),0) -> 388.53532
A52: MATERIAL DE LIMPIEZA | B52: =+IFERROR(VLOOKUP(A52,'T.D GASTOS'!$A$5:B57,2,0),0) -> 368.49272
A53: MARKETING GASTOS | B53: =+IFERROR(VLOOKUP(A53,'T.D GASTOS'!$A$5:B58,2,0),0) -> 15.078787
A54: MATERIAL DE OFICINA | B54: =+IFERROR(VLOOKUP(A54,'T.D GASTOS'!$A$5:B59,2,0),0) -> 19.752048
A55: MATERIALES DE FERRETERIA | B55: =+IFERROR(VLOOKUP(A55,'T.D GASTOS'!$A$5:B60,2,0),0) -> 0
A56: OTROS GASTOS ADMINISTRATIVOS | B56: =+IFERROR(VLOOKUP(A56,'T.D GASTOS'!$A$5:B60,2,0),0) -> 178
A57: =+'B.D.'!C54 -> PAGO 25% IVA | B57: =+IFERROR(VLOOKUP(A57,'T.D GASTOS'!$A$5:B60,2,0),0) -> 0
A58: PLATAFORMA DIGITAL | B58: =+IFERROR(VLOOKUP(A58,'T.D GASTOS'!$A$5:B60,2,0),0) -> 5369.4323
A59: RODAMIENTO PARA VEHICULOS | B59: =+IFERROR(VLOOKUP(A59,'T.D GASTOS'!$A$5:B61,2,0),0) -> 0
A60: SERVICIO MTTO DE VEHICULOS | B60: =+IFERROR(VLOOKUP(A60,'T.D GASTOS'!$A$5:B61,2,0),0) -> 472.91917
A61: SERVICIO TRANSPORTE | B61: =+IFERROR(VLOOKUP(A61,'T.D GASTOS'!$A$5:B61,2,0),0) -> 0
A62: SERVICIOS INFORMATICOS | B62: =+IFERROR(VLOOKUP(A62,'T.D GASTOS'!$A$5:B62,2,0),0) -> 0
A63: SERVICIOS TECNICOS | B63: =+IFERROR(VLOOKUP(A63,'T.D GASTOS'!$A$5:B63,2,0),0) -> 0
A64: SEGURIDAD | B64: =+IFERROR(VLOOKUP(A64,'T.D GASTOS'!$A$5:B64,2,0),0) -> 240
A65: SEGUROS | B65: =+IFERROR(VLOOKUP(A65,'T.D GASTOS'!$A$5:B65,2,0),0) -> 49.382406
A66: SERVICIOS DE GPS O SEGURIDAD | B66: =+IFERROR(VLOOKUP(A66,'T.D GASTOS'!$A$5:B66,2,0),0) -> 44.563452
A67: TRANSPORTE | B67: =+IFERROR(VLOOKUP(A67,'T.D GASTOS'!$A$5:B66,2,0),0) -> 0
C68: =SUM(B34:B68) -> 12263.733
A70: PRESTAMO BANCARIO | B70: =+IFERROR(VLOOKUP(A70,'T.D GASTOS'!$A$5:B66,2,0),0) -> 21316.463
A71: BANAVIH | B71: =+IFERROR(VLOOKUP(A71,'T.D GASTOS'!$A$5:B67,2,0),0) -> 14.494127
A72: IAE (ALCALDIA) | B72: =+IFERROR(VLOOKUP(A72,'T.D GASTOS'!$A$5:B68,2,0),0) -> 6418.4906
A73: IGTF | B73: =+IFERROR(VLOOKUP(A73,'T.D GASTOS'!$A$5:B69,2,0),0) -> 508.33475
A74: IMPUESTOS PUBLICIDAD | B74: =+IFERROR(VLOOKUP(A74,'T.D GASTOS'!$A$5:B70,2,0),0) -> 0
A75: INCES | B75: =+IFERROR(VLOOKUP(A75,'T.D GASTOS'!$A$5:B71,2,0),0) -> 27.35732
A76: ISLR ANTICIPADO | B76: =+IFERROR(VLOOKUP(A76,'T.D GASTOS'!$A$5:B72,2,0),0) -> 2430.8674
A77: ISLR DEFINITIVA | B77: =+IFERROR(VLOOKUP(A77,'T.D GASTOS'!$A$5:B73,2,0),0) -> 0
A78: IVA | B78: =+IFERROR(VLOOKUP(A78,'T.D GASTOS'!$A$5:B73,2,0),0) -> 2287.6603
A79: IVSS | B79: =+IFERROR(VLOOKUP(A79,'T.D GASTOS'!$A$5:B74,2,0),0) -> 7.1511463
A80: LEY DE PENSIONES | B80: =+IFERROR(VLOOKUP(A80,'T.D GASTOS'!$A$5:B75,2,0),0) -> 679.80615
A81: LEY DEL DEPORTE | B81: =+IFERROR(VLOOKUP(A81,'T.D GASTOS'!$A$5:B76,2,0),0) -> 0
A82: LOCTI | B82: =+IFERROR(VLOOKUP(A82,'T.D GASTOS'!$A$5:B76,2,0),0) -> 274.45862
A83: LRPE | B83: =+IFERROR(VLOOKUP(A83,'T.D GASTOS'!$A$5:B76,2,0),0) -> 0
A84: PERMISOLOGIA | B84: =+IFERROR(VLOOKUP(A84,'T.D GASTOS'!$A$5:B77,2,0),0) -> 540.58261
A85: RETENCION ISLR | B85: =+IFERROR(VLOOKUP(A85,'T.D GASTOS'!$A$5:B78,2,0),0) -> 142.33669
A86: RETENCIÓN IVA | B86: =+IFERROR(VLOOKUP(A86,'T.D GASTOS'!$A$5:B79,2,0),0) -> 22736.466
A87: RETENCIÓN MUNICIPAL | B87: =+IFERROR(VLOOKUP(A87,'T.D GASTOS'!$A$5:B80,2,0),0) -> 147.48014
A88: DONACIÓN | B88: =+IFERROR(VLOOKUP(A88,'T.D GASTOS'!$A$5:B81,2,0),0) -> 1079.4587
C89: =SUM(B70:B89) -> 58611.408
A91: TOTAL GASTOS | D91: =+C89+C68+C32 -> 80500.409
A93: RESULTADO DEL EJERCICIO AL 31-03-2026 | E93: =+E20-D91 -> 256515.58
A97: RENDIMIENTO AL 31-05-2026 | E97: =+E93 -> 256515.58
A100: INFORMATIVO
A101: =+INGRESOS!N29 -> 746.63
A102: **CUENTAS POR COBRAR | B102: FACTS | C102: =+GETPIVOTDATA("Suma de IMPORTE ADEUDADO",'CUENTAS POR COBRAR'!$P$6) -> 1254.67
B103: CASHEA | C103: =+'CUENTAS POR COBRAR'!H7 -> 47065.6
B104: NE | C104: =+'CUENTAS POR COBRAR'!N28 -> 19530.91 | E104: =SUM(C102:C104) -> 67851.18
A106: ** INGRESOS | B106: BS | C106: =+INGRESOS!F30+INGRESOS!G30+INGRESOS!H30+INGRESOS!I30+INGRESOS!J30+INGRESOS!K30 -> 3.2039084e+08
A107: EXPRESADO EN $$ | B107: ME | C107: =+INGRESOS!L30 -> 450068.32 | E107: =+C107 -> 450068.32
A109: ** SALDOS EN CAJA | B109: BS | C109: 15670
A110: EXPRESADO EN $$ | B110: ME | C110: 767.52358 | E110: =+C110 -> 767.52358
A112: ** SALDOS EN BANCO | B112: BS | C112: 8629984.5
B113: ME | C113: =+C112/A101 -> 11558.583 | E113: =+C113 -> 11558.583
A114: ** Los montos aquí reflejados son los que tenemos en control de verificación de registro.**
A115: **
A120: SALDOS EN BCOS PPLES (CON SALDOS INICIALES)

Sheet INGRESOS
B4: VENTAS BS | E4: RELACION DE ENTRADAS EXPRESADAS EN BS | P4: VENTAS EXPRESADA EN $
B5: REPORTE Z | D5: NOTAS DE ENTREGA | E5: IGTF | F5: EFECTIVO BOLIVARES | G5: BANCOS | H5: MONEDA EXTRANJERA | N5: TASA DE CAMBIO | U5: REPORTE Z
A6: FECHA | B6: BASE IMPONIBLE | C6: IVA | E6: IGTF | H6: USD | I6: ZELLE | J6: BINANCE | K6: BANESCO PANAMÁ | L6: INGRESO EXPRESADO EN $ | N6: USD | P6: VENTAS SIN IVA | Q6: VENTAS (CON IVA) | S6: VENTAS EN NE | U6: BASE IMPONIBLE | V6: IVA | W6: IGTF | Y6: ventas diarias en $ | Z6: DIF (VTAS-ING) | AB6: INGRESOS EN $ | AE6: Bs | AF6: Banco | AG6: $ | AH6: Zelle | AI6: Binance | AJ6: BP
A7: 46204 | B7: 8760063.6 | C7: =+B7*0.16 -> 1401610.2 | D7: =+S7*N7 -> 5845311.1 | E7: 0 | F7: 17108.401 | G7: 7611712.9 | H7: 6021712 | I7: 1359498.2 | J7: 607648.86 | K7: 0 | L7: =(F7+G7+H7+I7+J7+K7)/N7 -> 24658.457 | N7: 633.36 | P7: =+B7/N7 -> 13831.097 | Q7: =(B7+C7)/N7 -> 16044.073 | S7: 9229.05 | U7: =+B7/N7 -> 13831.097 | V7: =+C7/N7 -> 2212.9755 | W7: =+E7/N7 -> 0 | Y7: =+Q7+S7+W7 -> 25273.123 | Z7: =+Q7+S7+W7-L7 -> 614.6656 | AB7: =+(F7+G7)/N7 -> 12045 | AC7: =(H7+I7+J7)/N7 -> 12613.457 | AE7: =+F7/$N$7 -> 27.012128 | AF7: =+G7/N7 -> 12017.988 | AG7: =+H7/N7 -> 9507.566 | AH7: =+I7/N7 -> 2146.4857 | AI7: =+J7/N7 -> 959.40517 | AJ7: =+K7/N7 -> 0
A8: 46205 | B8: 6764656.3 | C8: =+B8*0.16 -> 1082345 | D8: =+S8*N8 -> 3967227.5 | E8: 3746.99 | F8: -237.5136 | G8: 6362320.3 | H8: 3029782.9 | I8: 1360648.6 | J8: 470774.22 | K8: 0 | L8: =(F8+G8+H8+I8+J8+K8)/N8 -> 17544.612 | N8: 639.7 | P8: =+B8/N8 -> 10574.732 | Q8: =(B8+C8)/N8 -> 12266.69 | S8: 6201.7 | U8: =+B8/N8 -> 10574.732 | V8: =+C8/N8 -> 1691.9572 | W8: =+E8/N8 -> 5.8574175 | Y8: =+Q8+S8+W8 -> 18474.247 | Z8: =+Q8+S8+W8-L8 -> 929.63483 | AB8: =+(F8+G8)/N8 -> 9945.4162 | AC8: =(H8+I8+J8)/N8 -> 7599.196 | AE8: =+F8/N8 -> -0.37128904 | AF8: =+G8/N8 -> 9945.7875 | AG8: =+H8/N8 -> 4736.2558 | AH8: =+I8/N8 -> 2127.0105 | AI8: =+J8/N8 -> 735.92969 | AJ8: =+K8/N8 -> 0
A9: 46206 | B9: 12290608 | C9: =+B9*0.16 -> 1966497.2 | D9: =+S9*N9 -> 3751071.1 | E9: 391.78 | F9: -6591.0024 | G9: 11960747 | H9: 1411721.5 | I9: 211854.71 | J9: 2523314.8 | K9: 0 | L9: =(F9+G9+H9+I9+J9+K9)/N9 -> 24658.173 | N9: 652.97 | P9: =+B9/N9 -> 18822.622 | Q9: =(B9+C9)/N9 -> 21834.242 | S9: 5744.63 | U9: =+B9/N9 -> 18822.622 | V9: =+C9/N9 -> 3011.6196 | W9: =+E9/N9 -> 0.59999694 | Y9: =+Q9+S9+W9 -> 27579.472 | Z9: =+Q9+S9+W9-L9 -> 2921.2992 | AB9: =+(F9+G9)/N9 -> 18307.359 | AC9: =(H9+I9+J9)/N9 -> 6350.8139 | AE9: =+F9/N9 -> -10.093882 | AF9: =+G9/N9 -> 18317.453 | AG9: =+H9/N9 -> 2162.0005 | AH9: =+I9/N9 -> 324.44784 | AI9: =+J9/N9 -> 3864.3656 | AJ9: =+K9/N9 -> 0
A10: 46209 | B10: 8975954 | C10: =+B10*0.16 -> 1436152.6 | D10: =+S10*N10 -> 6156237.8 | E10: 100.06 | F10: 39167.477 | G10: 7154996.1 | H10: 2140591.3 | I10: 4388501.7 | J10: 1108245.9 | K10: 0 | L10: =(F10+G10+H10+I10+J10+K10)/N10 -> 22234.469 | N10: 667.05 | P10: =+B10/N10 -> 13456.194 | Q10: =(B10+C10)/N10 -> 15609.185 | S10: =SUM(S6:S7) -> 9229.05 | U10: =+B10/N10 -> 13456.194 | V10: =+C10/N10 -> 2152.991 | W10: =+E10/N10 -> 0.15000375 | Y10: =+Q10+S10+W10 -> 24838.385 | Z10: =+Q10+S10+W10-L10 -> 2603.9159 | AB10: =+(F10+G10)/N10 -> 10785.044 | AC10: =(H10+I10+J10)/N10 -> 11449.425 | AE10: =+F10/N10 -> 58.717453 | AF10: =+G10/N10 -> 10726.326 | AG10: =+H10/N10 -> 3209.0418 | AH10: =+I10/N10 -> 6578.9696 | AI10: =+J10/N10 -> 1661.4135 | AJ10: =+K10/N10 -> 0
A11: 46210 | B11: 6969486.4 | C11: =+B11*0.16 -> 1115117.8 | D11: =+S11*N11 -> 5136149.8 | E11: 607.44 | F11: -10.36 | G11: 6229261.5 | H11: 2737344.2 | I11: 1980262.2 | J11: 693665.89 | K11: 16640.797 | L11: =(F11+G11+H11+I11+J11+K11)/N11 -> 17271.664 | N11: 674.93 | P11: =+B11/N11 -> 10326.236 | Q11: =(B11+C11)/N11 -> 11978.434 | S11: 7609.9 | U11: =+B11/N11 -> 10326.236 | V11: =+C11/N11 -> 1652.1978 | W11: =+E11/N11 -> 0.90000444 | Y11: =+Q11+S11+W11 -> 19589.234 | Z11: =+Q11+S11+W11-L11 -> 2317.5696 | AB11: =+(F11+G11)/N11 -> 9229.4773 | AC11: =(H11+I11+J11)/N11 -> 8017.5312 | AE11: =+F11/N11 -> -0.01534974 | AF11: =+G11/N11 -> 9229.4927 | AG11: =+H11/N11 -> 4055.7454 | AH11: =+I11/N11 -> 2934.0261 | AI11: =+J11/N11 -> 1027.7598 | AJ11: =+K11/N11 -> 24.655589
A12: 46211 | B12: 6945083.7 | C12: =+B12*0.16 -> 1111213.4 | D12: =+S12*N12 -> 2381480.8 | E12: 0 | F12: -2709.1395 | G12: 7059333.4 | H12: 999783.81 | I12: 222780.33 | J12: 515025.97 | K12: 0 | L12: =(F12+G12+H12+I12+J12+K12)/N12 -> 12820.676 | N12: 685.94 | P12: =+B12/N12 -> 10124.914 | Q12: =(B12+C12)/N12 -> 11744.901 | S12: 3471.85 | U12: =+B12/N12 -> 10124.914 | V12: =+C12/N12 -> 1619.9863 | W12: =+E12/N12 -> 0 | Y12: =+Q12+S12+W12 -> 15216.751 | Z12: =+Q12+S12+W12-L12 -> 2396.0747 | AB12: =+(F12+G12)/N12 -> 10287.524 | AC12: =(H12+I12+J12)/N12 -> 2533.1518 | AE12: =+F12/N12 -> -3.9495284 | AF12: =+G12/N12 -> 10291.474 | AG12: =+H12/N12 -> 1457.5383 | AH12: =+I12/N12 -> 324.78108 | AI12: =+J12/N12 -> 750.8324 | AJ12: =+K12/N12 -> 0
A13: 46212 | B13: 8489746.8 | C13: =+B13*0.16 -> 1358359.5 | D13: =+S13*N13 -> 3681350.6 | E13: 0 | F13: -1647.7506 | G13: 6677221.4 | H13: 875089.17 | I13: 1375263.1 | J13: 1526314.3 | K13: 0 | L13: =(F13+G13+H13+I13+J13+K13)/N13 -> 14927.08 | N13: 700.22 | P13: =+B13/N13 -> 12124.399 | Q13: =(B13+C13)/N13 -> 14064.303 | S13: 5257.42 | U13: =+B13/N13 -> 12124.399 | V13: =+C13/N13 -> 1939.9039 | W13: =+E13/N13 -> 0 | Y13: =+Q13+S13+W13 -> 19321.723 | Z13: =+Q13+S13+W13-L13 -> 4394.6426 | AB13: =+(F13+G13)/N13 -> 9533.5375 | AC13: =(H13+I13+J13)/N13 -> 5393.5429 | AE13: =+F13/N13 -> -2.3531899 | AF13: =+G13/N13 -> 9535.8907 | AG13: =+H13/N13 -> 1249.7346 | AH13: =+I13/N13 -> 1964.0443 | AI13: =+J13/N13 -> 2179.764 | AJ13: =+K13/N13 -> 0
A14: 46213 | B14: 11691997 | C14: =+B14*0.16 -> 1870719.5 | D14: =+S14*N14 -> 2490827.4 | E14: 0 | F14: -2085.6663 | G14: 10229770 | H14: 1117798.4 | I14: 1093928.3 | J14: 127886.23 | K14: 0 | L14: =(F14+G14+H14+I14+J14+K14)/N14 -> 17708.15 | N14: 709.69 | P14: =+B14/N14 -> 16474.794 | Q14: =(B14+C14)/N14 -> 19110.761 | S14: 3509.74 | U14: =+B14/N14 -> 16474.794 | V14: =+C14/N14 -> 2635.9671 | W14: =+E14/N14 -> 0 | Y14: =+Q14+S14+W14 -> 22620.501 | Z14: =+Q14+S14+W14-L14 -> 4912.3513 | AB14: =+(F14+G14)/N14 -> 14411.481 | AC14: =(H14+I14+J14)/N14 -> 3296.6688 | AE14: =+F14/N14 -> -2.9388413 | AF14: =+G14/N14 -> 14414.42 | AG14: =+H14/N14 -> 1575.0516 | AH14: =+I14/N14 -> 1541.417 | AI14: =+J14/N14 -> 180.20013 | AJ14: =+K14/N14 -> 0
A15: 46216 | B15: 22682124 | C15: =+B15*0.16 -> 3629139.8 | D15: =+S15*N15 -> 9139439.6 | E15: 373797.7 | F15: -1595.7945 | G15: 8376160.4 | H15: 14104367 | I15: 959918.64 | J15: 973746.38 | K15: 0 | L15: =(F15+G15+H15+I15+J15+K15)/N15 -> 33842.928 | N15: 721.35 | P15: =+B15/N15 -> 31443.993 | Q15: =(B15+C15)/N15 -> 36475.031 | S15: 12669.91 | U15: =+B15/N15 -> 31443.993 | V15: =+C15/N15 -> 5031.0388 | W15: =+E15/N15 -> 518.19186 | Y15: =+Q15+S15+W15 -> 49663.133 | Z15: =+Q15+S15+W15-L15 -> 15820.205 | AB15: =+(F15+G15)/N15 -> 11609.572 | AC15: =(H15+I15+J15)/N15 -> 22233.356 | AE15: =+F15/N15 -> -2.2122333 | AF15: =+G15/N15 -> 11611.784 | AG15: =+H15/N15 -> 19552.737 | AH15: =+I15/N15 -> 1330.7252 | AI15: =+J15/N15 -> 1349.8945 | AJ15: =+K15/N15 -> 0
A16: 46217 | B16: 18021337 | C16: =+B16*0.16 -> 2883414 | D16: =+S16*N16 -> 4774280.4 | E16: 0 | F16: -7949.2833 | G16: 16012804 | H16: 1920891.2 | I16: 1397960.5 | J16: 2069864.2 | K16: 0 | L16: =(F16+G16+H16+I16+J16+K16)/N16 -> 29549.131 | N16: 724 | P16: =+B16/N16 -> 24891.35 | Q16: =(B16+C16)/N16 -> 28873.966 | S16: 6594.31 | U16: =+B16/N16 -> 24891.35 | V16: =+C16/N16 -> 3982.616 | W16: =+E16/N16 -> 0 | Y16: =+Q16+S16+W16 -> 35468.276 | Z16: =+Q16+S16+W16-L16 -> 5919.1452 | AB16: =+(F16+G16)/N16 -> 22106.153 | AC16: =(H16+I16+J16)/N16 -> 7442.9779 | AE16: =+F16/N16 -> -10.979673 | AF16: =+G16/N16 -> 22117.132 | AG16: =+H16/N16 -> 2653.1647 | AH16: =+I16/N16 -> 1930.8847 | AI16: =+J16/N16 -> 2858.9285 | AJ16: =+K16/N16 -> 0
A17: 46218 | B17: 6540811.2 | C17: =+B17*0.16 -> 1046529.8 | D17: =+S17*N17 -> 4292608 | E17: 0 | F17: -7578.1683 | G17: 6504336.9 | H17: 1235812.9 | I17: 289722.06 | J17: 3734025.5 | K17: 0 | L17: =(F17+G17+H17+I17+J17+K17)/N17 -> 16198.855 | N17: 725.75 | P17: =+B17/N17 -> 9012.4852 | Q17: =(B17+C17)/N17 -> 10454.483 | S17: 5914.72 | U17: =+B17/N17 -> 9012.4852 | V17: =+C17/N17 -> 1441.9976 | W17: =+E17/N17 -> 0 | Y17: =+Q17+S17+W17 -> 16369.203 | Z17: =+Q17+S17+W17-L17 -> 170.34755 | AB17: =+(F17+G17)/N17 -> 8951.786 | AC17: =(H17+I17+J17)/N17 -> 7247.0693 | AE17: =+F17/N17 -> -10.441844 | AF17: =+G17/N17 -> 8962.2279 | AG17: =+H17/N17 -> 1702.8081 | AH17: =+I17/N17 -> 399.20366 | AI17: =+J17/N17 -> 5145.0576 | AJ17: =+K17/N17 -> 0
A18: 46219 | B18: 10276381 | C18: =+B18*0.16 -> 1644220.9 | D18: =+S18*N18 -> 8930212.6 | E18: 0 | F18: -5091.6978 | G18: 7194105.7 | H18: 5480626.3 | I18: 1367365.8 | J18: 2412366.3 | K18: 0 | L18: =(F18+G18+H18+I18+J18+K18)/N18 -> 22612.375 | N18: 727.45 | P18: =+B18/N18 -> 14126.58 | Q18: =(B18+C18)/N18 -> 16386.833 | S18: 12276.05 | U18: =+B18/N18 -> 14126.58 | V18: =+C18/N18 -> 2260.2528 | W18: =+E18/N18 -> 0 | Y18: =+Q18+S18+W18 -> 28662.883 | Z18: =+Q18+S18+W18-L18 -> 6050.5078 | AB18: =+(F18+G18)/N18 -> 9882.4854 | AC18: =(H18+I18+J18)/N18 -> 12729.89 | AE18: =+F18/N18 -> -6.9993784 | AF18: =+G18/N18 -> 9889.4848 | AG18: =+H18/N18 -> 7534.0248 | AH18: =+I18/N18 -> 1879.6698 | AI18: =+J18/N18 -> 3316.1953 | AJ18: =+K18/N18 -> 0
A19: 46220 | B19: 6374960.7 | C19: =+B19*0.16 -> 1019993.7 | D19: =+S19*N19 -> 6990115.2 | E19: 1098.72 | F19: 7038.5671 | G19: 4523899.4 | H19: 2234854.5 | I19: 1704293.7 | J19: 3001340.6 | K19: 0 | L19: =(F19+G19+H19+I19+J19+K19)/N19 -> 15661.079 | N19: 732.48 | P19: =+B19/N19 -> 8703.2556 | Q19: =(B19+C19)/N19 -> 10095.776 | S19: 9543.08 | U19: =+B19/N19 -> 8703.2556 | V19: =+C19/N19 -> 1392.5209 | W19: =+E19/N19 -> 1.5 | Y19: =+Q19+S19+W19 -> 19640.356 | Z19: =+Q19+S19+W19-L19 -> 3979.2779 | AB19: =+(F19+G19)/N19 -> 6185.7498 | AC19: =(H19+I19+J19)/N19 -> 9475.3288 | AE19: =+F19/N19 -> 9.6092277 | AF19: =+G19/N19 -> 6176.1406 | AG19: =+H19/N19 -> 3051.0793 | AH19: =+I19/N19 -> 2326.7443 | AI19: =+J19/N19 -> 4097.5052 | AJ19: =+K19/N19 -> 0
A20: 46223 | B20: 9900725.6 | C20: =+B20*0.16 -> 1584116.1 | D20: =+S20*N20 -> 5814090.3 | E20: 0 | F20: -1462.1931 | G20: 7617639.6 | H20: 1948353.8 | I20: 1023204.1 | J20: 2808108.4 | K20: 42232.887 | L20: =(F20+G20+H20+I20+J20+K20)/N20 -> 18235.215 | N20: 736.93 | P20: =+B20/N20 -> 13435.096 | Q20: =(B20+C20)/N20 -> 15584.712 | S20: 7889.61 | U20: =+B20/N20 -> 13435.096 | V20: =+C20/N20 -> 2149.6154 | W20: =+E20/N20 -> 0 | Y20: =+Q20+S20+W20 -> 23474.322 | Z20: =+Q20+S20+W20-L20 -> 5239.1072 | AB20: =+(F20+G20)/N20 -> 10335.008 | AC20: =(H20+I20+J20)/N20 -> 7842.8973 | AE20: =+F20/N20 -> -1.9841682 | AF20: =+G20/N20 -> 10336.992 | AG20: =+H20/N20 -> 2643.879 | AH20: =+I20/N20 -> 1388.4686 | AI20: =+J20/N20 -> 3810.5498 | AJ20: =+K20/N20 -> 57.309225
A21: 46224 | B21: 15377673 | C21: =+B21*0.16 -> 2460427.6 | D21: =+S21*N21 -> 7407635.4 | E21: 1150.08 | F21: -1358.2809 | G21: 12524266 | H21: 2278646.1 | I21: 549242.78 | J21: 1473267.2 | K21: 0 | L21: =(F21+G21+H21+I21+J21+K21)/N21 -> 22820.644 | N21: 737.23 | P21: =+B21/N21 -> 20858.718 | Q21: =(B21+C21)/N21 -> 24196.113 | S21: 10047.93 | U21: =+B21/N21 -> 20858.718 | V21: =+C21/N21 -> 3337.3949 | W21: =+E21/N21 -> 1.5600016 | Y21: =+Q21+S21+W21 -> 34245.603 | Z21: =+Q21+S21+W21-L21 -> 11424.958 | AB21: =+(F21+G21)/N21 -> 16986.432 | AC21: =(H21+I21+J21)/N21 -> 5834.2119 | AE21: =+F21/N21 -> -1.8424113 | AF21: =+G21/N21 -> 16988.275 | AG21: =+H21/N21 -> 3090.8212 | AH21: =+I21/N21 -> 745.00872 | AI21: =+J21/N21 -> 1998.382 | AJ21: =+K21/N21 -> 0
A22: 46225 | B22: 11406801 | C22: =+B22*0.16 -> 1825088.1 | D22: =+S22*N22 -> 6250936.3 | E22: 36759.84 | F22: 0 | G22: 6796648.7 | H22: 1856317.2 | I22: 1351682.5 | J22: 2849124.1 | K22: 0 | L22: =(F22+G22+H22+I22+J22+K22)/N22 -> 17435.227 | N22: 737.23 | P22: =+B22/N22 -> 15472.513 | Q22: =(B22+C22)/N22 -> 17948.115 | S22: 8478.95 | U22: =+B22/N22 -> 15472.513 | V22: =+C22/N22 -> 2475.602 | W22: =+E22/N22 -> 49.862105 | Y22: =+Q22+S22+W22 -> 26476.927 | Z22: =+Q22+S22+W22-L22 -> 9041.6997 | AB22: =+(F22+G22)/N22 -> 9219.17 | AC22: =(H22+I22+J22)/N22 -> 8216.0571 | AE22: =+F22/N22 -> 0 | AF22: =+G22/N22 -> 9219.17 | AG22: =+H22/N22 -> 2517.9621 | AH22: =+I22/N22 -> 1833.461 | AI22: =+J22/N22 -> 3864.6339 | AJ22: =+K22/N22 -> 0
... A24: 46227 | B24: 3835425.1 | C24: =+B24*0.16 -> 613668.01 | D24: =+S24*N24 -> 5965354.5 | E24: 0 | F24: 0 | G24: 3189821.4 | H24: 390412.98 | I24: 1781730.5 | J24: 3786352.7 | K24: 0 | L24: =(F24+G24+H24+I24+J24+K24)/N24 -> 12325.448 | N24: 742.23 | P24: =+B24/N24 -> 5167.4347 | Q24: =(B24+C24)/N24 -> 5994.2243 | S24: 8037.07 | U24: =+B24/N24 -> 5167.4347 | V24: =+C24/N24 -> 826.78956 | W24: =+E24/N24 -> 0 | Y24: =+Q24+S24+W24 -> 14031.294 | Z24: =+Q24+S24+W24-L24 -> 1705.8458 | AB24: =+(F24+G24)/N24 -> 4297.6185 | AC24: =(H24+I24+J24)/N24 -> 8027.83 | AE24: =+F24/N24 -> 0 | AF24: =+G24/N24 -> 4297.6185 | AG24: =+H24/N24 -> 526 | AH24: =+I24/N24 -> 2400.51 | AI24: =+J24/N24 -> 5101.32 | AJ24: =+K24/N24 -> 0
A25: 46230 | B25: 9637108.9 | C25: =+B25*0.16 -> 1541937.4 | D25: =+S25*N25 -> 5438853.6 | E25: 2063.62 | F25: 779.3415 | G25: 8825520.9 | H25: 2168053.8 | I25: 468703.4 | J25: 2158070.8 | K25: 277052.19 | L25: =(F25+G25+H25+I25+J25+K25)/N25 -> 18724.897 | N25: 742.23 | P25: =+B25/N25 -> 12983.993 | Q25: =(B25+C25)/N25 -> 15061.432 | S25: 7327.72 | V25: =+C25/N25 -> 2077.4388 | W25: =+E25/N25 -> 2.7802972
A26: 46231 | B26: 10767261 | C26: =+B26*0.16 -> 1722761.8 | D26: =+S26*N26 -> 4011857.4 | E26: 0 | F26: 11415.497 | G26: 9026472.6 | H26: 1760569.6 | I26: 821990.04 | J26: 1424443.3 | K26: 0 | L26: =(F26+G26+H26+I26+J26+K26)/N26 -> 17561.545 | N26: 742.81 | P26: =+B26/N26 -> 14495.31 | Q26: =(B26+C26)/N26 -> 16814.559 | S26: 5400.92 | V26: =+C26/N26 -> 2319.2496 | W26: =+E26/N26 -> 0
A27: 46232 | B27: 8972038.1 | C27: =+B27*0.16 -> 1435526.1 | D27: =+S27*N27 -> 14357574 | E27: 1562.86 | F27: -3057.9876 | G27: 7193171.8 | H27: 1622514.8 | I27: 846283.22 | J27: 2997725.9 | K27: 0 | L27: =(F27+G27+H27+I27+J27+K27)/N27 -> 17006.581 | N27: 744.22 | P27: =+B27/N27 -> 12055.626 | Q27: =(B27+C27)/N27 -> 13984.526 | S27: 19292.11 | V27: =+C27/N27 -> 1928.9002 | W27: =+E27/N27 -> 2.0999973
A28: 46233 | B28: 6300043.4 | C28: =+B28*0.16 -> 1008007 | D28: =+S28*N28 -> 3566785.7 | E28: 447.38 | F28: -8157.1077 | G28: 5296798.5 | H28: 1345663 | I28: 1072188.3 | J28: 1100370.8 | K28: 0 | L28: =(F28+G28+H28+I28+J28+K28)/N28 -> 11810.672 | N28: 745.67 | P28: =+B28/N28 -> 8448.8359 | Q28: =(B28+C28)/N28 -> 9800.6496 | S28: 4783.33 | V28: =+C28/N28 -> 1351.8137 | W28: =+E28/N28 -> 0.5999705
A29: 46234 | B29: 5394037.5 | C29: =+B29*0.16 -> 863046.01 | D29: =+S29*N29 -> 19231800 | E29: 0 | F29: 81.6453 | G29: 4262883.7 | H29: 2200712 | I29: 4793833.5 | J29: 4600252.5 | K29: 0 | L29: =(F29+G29+H29+I29+J29+K29)/N29 -> 21239.119 | N29: 746.63 | P29: =+B29/N29 -> 7224.5122 | Q29: =(B29+C29)/N29 -> 8380.4341 | S29: 25758.14 | V29: =+C29/N29 -> 1155.9219 | W29: =+E29/N29 -> 0
A30: bs | B30: =SUM(B7:B29) -> 2.2793362e+08 | C30: =SUM(C7:C29) -> 36469379 | D30: =SUM(D7:D29) -> 1.4681308e+08 | E30: =SUM(E7:E29) -> 421726.47 | F30: =SUM(F7:F29) -> 26229.697 | G30: =SUM(G7:G29) -> 1.8256033e+08 | H30: =SUM(H7:H29) -> 59640919 | I30: =SUM(I7:I29) -> 30920355 | ... L30: =SUM(L7:L29) -> 450068.32 | P30: =SUM(P7:P29) -> 319720.24 | Q30: =SUM(Q7:Q29) -> 370875.48 | R30: =SUM(R7:R29) -> 0 | S30: =SUM(S7:S29) -> 204068.08 | U30: =SUM(U7:U24) -> 264511.97 | V30: =SUM(V7:V29) -> 51155.239 | W30: =SUM(W7:W29) -> 584.10166 | Y30: =SUM(Y7:Y24) -> 448918.36 | Z30: =SUM(Z7:Z24) -> 85192.855 | AB30: =SUM(AB7:AB24) -> 210287.57 | AC30: =SUM(AC7:AC24) -> 153287.57 | AE30: =SUM(AE7:AE24) -> 41.388376 | AF30: =SUM(AF7:AF24) -> 210246.19 | AG30: =SUM(AG7:AG24) -> 72254.441 | AH30: =SUM(AH7:AH24) -> 32852.795 | AI30: =SUM(AI7:AI24) -> 48180.331 | AJ30: =SUM(AJ7:AJ24) -> 150.36569
A31: $ | B31: =+P30 -> 319720.24 | C31: =+V30 -> 51155.239 | D31: =+S30 -> 204068.08 | E31: =+W30 -> 584.10166 | F31: =+AE30 -> 41.388376 | G31: =+AF30 -> 210246.19 | H31: =+AG30 -> 72254.441 | I31: =+AH30 -> 32852.795 | J31: =+AI30 -> 48180.331 | K31: =+AJ30 -> 150.36569
P32: FACTS | Q32: =+P30 -> 319720.24
A33: declrado vrs reportes | B33: 0 | E33: 0 | G33: 0
B34: =+B30-B33 -> 2.2793362e+08 | P34: NE | Q34: =+S30 -> 204068.08
P36: total ventas | Q36: =SUM(Q32:Q35) -> 523788.32
E40: fct | F40: ne | G40: bcos | H40: $
E41: =SUM(E37:E38) -> 0 | F41: =SUM(F37:F38) -> 0 | G41: =SUM(G37:G38) -> 0
G43: =SUM(E43:F43) -> 0 | H43: =+G43*$N$24 -> 0 | I43: Bs
G44: =SUM(E44:F44) -> 0 | H44: =+G44*$N$24 -> 0 | I44: $
G45: =SUM(E45:F45) -> 0 | H45: =+G45*$N$24 -> 0 | I45: zelle
G46: =SUM(E46:F46) -> 0 | H46: =+G46*$N$24 -> 0 | I46: binance
G47: =SUM(E47:F47) -> 0 | H47: =+G47*$N$24 -> 0 | I47: bp

Sheet CUENTAS POR COBRAR
B2: Cuentas Por Cobrar Del 01/07/2026 Hasta 31/07/2026 | R2: OnProtec · Cuentas por cobrar
M3: OnProtec · Cuentas por cobrar NE
B6: CXC CASHEA | D6: TOTAL BOLIVARES | E6: TASA BCV AL 31/07/2026 | F6: TOTAL $ | P6: Etiquetas de fila | Q6: Suma de BASE | R6: Suma de IVA | S6: Suma de TOTAL | T6: Suma de IMPORTE ADEUDADO
B7: julio | D7: =+F14 -> 35131176 | E7: 746.43 | F7: =+D7/E7 -> 47065.6 | H7: =+F7 -> 47065.6 | L7: Etiquetas de fila | M7: Suma de Total | N7: Suma de Importe adeudado | P7: RETENCION EN TIENDA | Q7: 3169.18 | R7: 507.0688 | S7: 3676.2488 | T7: 389.95
D8: 0 | E8: , | K8: 1 | L8: Alfredo Gomez | M8: 634.05 | N8: 234.05 | P8: 46233 | Q8: 2938.51 | R8: 470.1616 | S8: 3408.6716 | T8: 362.27
K9: 2 | L9: Carlos A Martins D | M9: 324.22 | N9: 324.22 | P9: Mifar Farmaceutica, C.A. | Q9: 562.3 | R9: 89.968 | S9: 652.268 | T9: 74.51
E10: $ | K10: 3 | L10: Carlos Martins | M10: 9.48 | N10: 9.48 | P10: OPERACIONES LA CANDELARIA C.A | Q10: 207.75 | R10: 33.24 | S10: 240.99 | T10: 27.53
D11: ventas julio | E11: =+'[1]Detalles del reporte'!I27 -> 57238.53 | K11: 4 | L11: Comercializadora Grupo Plus, C.A. | M11: 5647.1 | N11: 5647.1 | P11: Droguería Mega C.A. | Q11: 162.92 | R11: 26.0672 | S11: 188.9872 | T11: 19.55
D12: Banco | E12: -46470.05 | K12: 5 | L12: Copikon Venezuela, C.A. | M12: 559.38 | N12: 116.7 | P12: CORPODIAGNOSTICA C.A. | Q12: 36.72 | R12: 5.8752 | S12: 42.5952 | T12: 4.41
D13: cuentas por cobrar a junio | E13: 36297.12 | K13: 6 | L13: Corporacion Eminent Pc C.A | M13: 564.21 | N13: 564.21 | P13: Rl Seguridad Y Sistemas C.A | Q13: 357.74 | R13: 57.2384 | S13: 414.9784 | T13: 42.93
D14: total cuenta por cobrar | E14: =SUM(E11:E13) -> 47065.6 | F14: =+E14*E7 -> 35131176 | K14: 7 | L14: DAHUA TECHNOLOGY(HK) LIMITED | M14: 586.34 | N14: 586.34 | P14: Minidepositos Alcatraz, C.A. | Q14: 229.3 | R14: 36.688 | S14: 265.988 | T14: 27.52
K15: 8 | L15: Emilio J Perez B | M15: 393.39 | N15: 393.39 | P15: LRG SERV, C.A. | Q15: 672.36 | R15: 107.5776 | S15: 779.9376 | T15: 80.69
K16: 9 | L16: Enrique Mezzina | M16: 7517.6 | N16: 5681.54 | P16: Dimsop Technology Ve, C.A | Q16: 491.78 | R16: 78.6848 | S16: 570.4648 | T16: 59.01
K17: 10 | L17: Industrias Dekotiendas L.C. C.A. | M17: 521.26 | N17: 521.26 | P17: ECOPOSADA & SPA SIETE MARES C.A. | Q17: 12 | R17: 1.92 | S17: 13.92 | T17: 1.44
K18: 11 | L18: Inversiones Miyjop C.A. | M18: 723.77 | N18: 583.52 | P18: AUTOMERCADO LOS MOLINOS C.A. | Q18: 205.64 | R18: 32.9024 | S18: 238.5424 | T18: 24.68
K19: 12 | L19: Jesús Bigorra | M19: 534 | N19: 534 | P19: 46232 | Q19: 230.67 | R19: 36.9072 | S19: 267.5772 | T19: 27.68
K20: 13 | L20: Jorge Estrella | M20: 165.2 | N20: 165.2 | P20: Aton Technology,C.A. | Q20: 230.67 | R20: 36.9072 | S20: 267.5772 | T20: 27.68
K21: 14 | L21: Juan Carlos Bastardo | M21: 255.88 | N21: 255.88 | P21: PENDIENTE POR RETENCION - PAGO | Q21: 324.12 | R21: 51.8592 | S21: 375.9792 | T21: 90.83
K22: 15 | L22: Juan Carlos Marquez | M22: 98.28 | N22: 48.28 | P22: 46233 | Q22: 324.12 | R22: 51.8592 | S22: 375.9792 | T22: 90.83
K23: 16 | L23: Power Link Corp, C.A. | M23: 645.76 | N23: 645.76 | P23: Bioclon, C.A. | Q23: 324.12 | R23: 51.8592 | S23: 375.9792 | T23: 90.83
K24: 17 | L24: Seintec, C.A | M24: 2922.42 | N24: 2922.42 | P24: NO PAGADA | Q24: 744.13 | R24: 119.0608 | S24: 863.1908 | T24: 773.89
K25: 18 | L25: SERVICIOS DE PROYECTOS Y CONSULTORIA SGSI 0526, C.A | M25: 219.36 | N25: 203.24 | P25: 46232 | Q25: 744.13 | R25: 119.0608 | S25: 863.1908 | T25: 773.89
K26: 19 | L26: Wr Servicios C.A | M26: 90.2 | N26: 90.2 | P26: Inversiones Prosetel, C.A. | Q26: 744.13 | R26: 119.0608 | S26: 863.1908 | T26: 773.89
K27: 20 | L27: Soluciones Innorbis, C.A. | M27: 4.44 | N27: 4.12 | P27: Total general | Q27: 4237.43 | R27: 677.9888 | S27: 4915.4188 | T27: 1254.67
L28: Total general | M28: 22416.34 | N28: 19530.91

Sheet Hoja1
A1: IT | B1: FECHA FACTURA | C1: PROVEEDOR | D1: RIF | E1: TIPO DE COMPRA | F1: NOTA DE ENTREGA | G1: Nº FT | H1: Nº CONTROL | I1: EXENTO | J1: BASE IMPONIBLE | K1: IVA | L1: % RET. IVA | M1: RETENCIÓN IVA | N1: A PAGAR | O1: TASA DE CAMBIO | P1: USD | Q1: T / E
B2: 44627 | C2: CARMEN RAMIREZ | E2: HARINA | F2: 114 | K2: 0 | M2: 0 | N2: 0 | O2: 1 | P2: 0
K3: 0 | M3: 0 | N3: 0 | O3: 1 | P3: 0
K4: 0 | M4: 0 | N4: 0 | O4: 1 | P4: 0
K5: 0 | M5: 0 | N5: 0 | O5: 1 | P5: 0
K6: 0 | M6: 0 | N6: 0 | O6: 1 | P6: 0
K7: 0 | M7: 0 | N7: 0 | O7: 1 | P7: 0
K8: 0 | M8: 0 | N8: 0 | O8: 1 | P8: 0
K9: 0 | M9: 0 | N9: 0 | O9: 1 | P9: 0
K10: 0 | M10: 0 | N10: 0 | O10: 1 | P10: 0
K11: 0 | M11: 0 | N11: 0 | O11: 1 | P11: 0
K12: 0 | M12: 0 | N12: 0 | O12: 1 | P12: 0
K13: 0 | M13: 0 | N13: 0 | O13: 1 | P13: 0
K14: 0 | M14: 0 | N14: 0 | O14: 1 | P14: 0
... K79: 0 | M79: 0 | N79: 0 | O79: 1 | P79: 0
I80: 2940.45 | J80: 0 | K80: 0 | M80: 0 | N80: 3101.4348 | P80: 0
A81: 1 | B81: 44622 | C81: AUTOMERCADOS PLAZAS | D81: J306725024 | E81: CARNE | G81: 52740 | I81: 154 | K81: 0 | L81: 0 | M81: 0 | N81: 154 | O81: 4.38 | P81: 35.159817 | Q81: USD
A82: 2 | B82: 44622 | C82: COCHE | E82: FRUTAS Y HORTALIZAS | I82: 692 | K82: 0 | M82: 0 | N82: 692 | O82: 4.38 | P82: 157.99087 | Q82: USD
B83: 44625 | C83: BODEGON DE OISES | E83: FRUTOS SECOS | G83: 973 | I83: 1582 | K83: 0 | M83: 0 | N83: 1582 | O83: 4.52 | P83: 350 | Q83: USD
B84: 44626 | C84: AUTOMERCADOS PLAZAS | D84: J306725024 | E84: CARNE | G84: 53833 | I84: 226 | K84: 0 | M84: 0 | N84: 226 | O84: 4.52 | P84: 50 | Q84: USD
B85: 44627 | C85: JAVIER ESPEJO | E85: PAPELERIA | F85: 3128 | I85: 238 | K85: 0 | M85: 0 | N85: 238 | O85: 4.32 | P85: 55.092593 | Q85: USD
B86: 44623 | C86: EXCELSIOR GAMMA | D86: J301420608 | E86: PESCADO | G86: 53545 | J86: 56.07 | K86: 8.9712 | M86: 0 | N86: 65.0412 | O86: 4.36 | P86: 14.917706 | Q86: BOLIVARES
B87: 44624 | C87: VARIOS PROVEEDORES | E87: VIVERES | G87: 010989/018879 | I87: 48.45 | J87: 82.71 | K87: 13.2336 | M87: 0 | N87: 144.3936 | O87: 4.52 | P87: 31.945487 | Q87: BOLIVARES

Sheet COMPRAS FACT
A4: RELACION DE COMPRAS (DESEMBOLSO)
A6: IT | B6: FECHA FACTURA | C6: PROVEEDOR | D6: TIPO DE COMPRA | E6: NOTA DE ENTREGA | F6: Nº FT | G6: EXENTO | H6: BASE IMPONIBLE | I6: IVA | J6: % RET. IVA | K6: RETENCIÓN IVA | L6: A PAGAR | M6: TASA DE CAMBIO | N6: USD | O6: PAGADO BS | P6: T / P | Q6: DEL MES | R6: FECHA DE PAGO | S6: OBSERVACIONES
B7: 46210 | C7: Seintec, C.A. | D7: REPOSICION DE MERCANCIA | M7: 778 | N7: 103001 | O7: =+Tabla7[[#This Row],[USD]]*Tabla7[[#This Row],[TASA DE CAMBIO]] -> 80134778 | P7: BANCOS | Q7: SI | R7: 46210 | S7: PAGO FACT (REPOSICION DE MERCANCIA)
B8: 46210 | C8: Servicios y Proyectos Radalcom, C.A. | D8: REPOSICION DE MERCANCIA | M8: 755 | N8: 480 | O8: =+Tabla7[[#This Row],[USD]]*Tabla7[[#This Row],[TASA DE CAMBIO]] -> 362400 | P8: BANCOS | Q8: SI | R8: 46210 | S8: PAGO FACT (REPOSICION DE MERCANCIA)
B9: 46211 | C9: Global Sarpi, C.A. | D9: REPOSICION DE MERCANCIA | M9: 800 | N9: 953.81 | O9: =+Tabla7[[#This Row],[USD]]*Tabla7[[#This Row],[TASA DE CAMBIO]] -> 763048 | P9: BANCOS | Q9: SI | R9: 46211 | S9: PAGO FACT REPOSICION DE MERCANCIA
B10: 46211 | C10: Inversiones Comtek, C.A. | D10: REPOSICION DE MERCANCIA | M10: 804 | N10: 1039.55 | O10: =+Tabla7[[#This Row],[USD]]*Tabla7[[#This Row],[TASA DE CAMBIO]] -> 835798.2 | P10: BANCOS | Q10: SI | R10: 46211 | S10: PAGO FACT REPOSICION DE MERCANCIA
B11: 46212 | C11: INVERSIONES COMTEK | D11: PAGO 25% IVA | M11: 700.22 | N11: 47.744894 | O11: =+Tabla7[[#This Row],[USD]]*Tabla7[[#This Row],[TASA DE CAMBIO]] -> 33431.93 | P11: BANCOS | Q11: SI | R11: 46212 | S11: PAGO 25% IVA
B12: 46212 | C12: GLOBAL SARPI | D12: PAGO 25% IVA | M12: 700.22 | N12: 43.589043 | O12: =+Tabla7[[#This Row],[USD]]*Tabla7[[#This Row],[TASA DE CAMBIO]] -> 30521.92 | P12: BANCOS | Q12: SI | R12: 46212 | S12: PAGO 25% IVA
B13: 46212 | C13: RADALCOM | D13: PAGO 25% IVA | M13: 700.22 | N13: 14.23267 | O13: =+Tabla7[[#This Row],[USD]]*Tabla7[[#This Row],[TASA DE CAMBIO]] -> 9966 | P13: BANCOS | Q13: SI | R13: 46212 | S13: PAGO 25% IVA
B14: 46212 | C14: SEINTEC | D14: PAGO 25% IVA | M14: 700.22 | N14: 4577.6915 | O14: =+Tabla7[[#This Row],[USD]]*Tabla7[[#This Row],[TASA DE CAMBIO]] -> 3205391.1 | P14: BANCOS | Q14: SI | R14: 46212 | S14: PAGO 25% IVA
B15: 46216 | C15: Grupo Comercial Tech, C.A. | D15: REPOSICION DE MERCANCIA | M15: 820 | N15: 3703.7 | O15: =+Tabla7[[#This Row],[USD]]*Tabla7[[#This Row],[TASA DE CAMBIO]] -> 3037034 | P15: BANCOS | Q15: SI | R15: 46216 | S15: PAGO FACT (REPOSICION DE MERCANCIA)
B16: 46216 | C16: DISTRIBUIDORA EMITECH | D16: REPOSICION DE MERCANCIA | M16: 830 | N16: 7353.79 | O16: =+Tabla7[[#This Row],[USD]]*Tabla7[[#This Row],[TASA DE CAMBIO]] -> 6103645.7 | P16: BANCOS | Q16: SI | R16: 46216 | S16: PAGO FACT (REPOSICION DE MERCANCIA)
B17: 46216 | C17: Copikon Banesco, C.A. | D17: REPOSICION DE MERCANCIA | M17: 824.57 | N17: 359.6 | O17: =+Tabla7[[#This Row],[USD]]*Tabla7[[#This Row],[TASA DE CAMBIO]] -> 296515.37 | P17: BANCOS | Q17: SI | R17: 46216 | S17: PAGO FACT (REPOSICION DE MERCANCIA)
B18: 46216 | C18: Venepac 2020, C.A. BANC BANESCO | D18: REPOSICION DE MERCANCIA | M18: 771.9 | N18: 6223.9219 | O18: =+Tabla7[[#This Row],[USD]]*Tabla7[[#This Row],[TASA DE CAMBIO]] -> 4804245.3 | P18: BANCOS | Q18: SI | R18: 46216 | S18: PAGO FACT (REPOSICION DE MERCANCIA)
... B37: 46234 | C37: VENEPAC | D37: PAGO 25% IVA | M37: 746.63 | N37: 939.22918 | O37: =+Tabla7[[#This Row],[USD]]*Tabla7[[#This Row],[TASA DE CAMBIO]] -> 701256.68 | P37: BANCOS | Q37: SI | R37: 46234 | S37: 25 % DE IVA FACTS 29725-29724-29723-29722-29721-29720
O38: =+Tabla7[[#This Row],[USD]]*Tabla7[[#This Row],[TASA DE CAMBIO]] -> 0
O39: =+Tabla7[[#This Row],[USD]]*Tabla7[[#This Row],[TASA DE CAMBIO]] -> 0
O40: =+Tabla7[[#This Row],[USD]]*Tabla7[[#This Row],[TASA DE CAMBIO]] -> 0
O41: =+Tabla7[[#This Row],[USD]]*Tabla7[[#This Row],[TASA DE CAMBIO]] -> 0
B42: 46094 | O42: =+Tabla7[[#This Row],[USD]]*Tabla7[[#This Row],[TASA DE CAMBIO]] -> 0 | P42: BANCOS | Q42: SI | R42: 46157 | S42: PAGO FACT (REPOSICION DE MERCANCIA)
B43: 46097 | O43: =+Tabla7[[#This Row],[USD]]*Tabla7[[#This Row],[TASA DE CAMBIO]] -> 0 | P43: BANCOS | Q43: SI | R43: 46157 | S43: PAGO FACT (REPOSICION DE MERCANCIA)
B44: 46097 | O44: =+Tabla7[[#This Row],[USD]]*Tabla7[[#This Row],[TASA DE CAMBIO]] -> 0 | P44: BANCOS | Q44: SI | R44: 46157 | S44: PAGO FACT (REPOSICION DE MERCANCIA)
B45: 46097 | O45: =+Tabla7[[#This Row],[USD]]*Tabla7[[#This Row],[TASA DE CAMBIO]] -> 0 | P45: BANCOS | Q45: SI | R45: 46157 | S45: PAGO FACT (REPOSICION DE MERCANCIA)
B46: 46097 | O46: =+Tabla7[[#This Row],[USD]]*Tabla7[[#This Row],[TASA DE CAMBIO]] -> 0 | P46: BANCOS | Q46: SI | R46: 46157 | S46: PAGO FACT (REPOSICION DE MERCANCIA)
B47: 46097 | O47: =+Tabla7[[#This Row],[USD]]*Tabla7[[#This Row],[TASA DE CAMBIO]] -> 0 | P47: BANCOS | Q47: SI | R47: 46157 | S47: PAGO FACT (REPOSICION DE MERCANCIA)
B48: 46097 | O48: =+Tabla7[[#This Row],[USD]]*Tabla7[[#This Row],[TASA DE CAMBIO]] -> 0 | P48: BANCOS | Q48: SI | R48: 46157 | S48: PAGO FACT (REPOSICION DE MERCANCIA)
B49: 46101 | O49: =+Tabla7[[#This Row],[USD]]*Tabla7[[#This Row],[TASA DE CAMBIO]] -> 0 | P49: BANCOS | Q49: SI | R49: 46157 | S49: PAGO FACT (REPOSICION DE MERCANCIA)
B50: 46102 | O50: =+Tabla7[[#This Row],[USD]]*Tabla7[[#This Row],[TASA DE CAMBIO]] -> 0 | P50: BANCOS | Q50: SI | R50: 46157 | S50: PAGO FACT (REPOSICION DE MERCANCIA)
B51: 46106 | O51: =+Tabla7[[#This Row],[USD]]*Tabla7[[#This Row],[TASA DE CAMBIO]] -> 0 | P51: BANCOS | Q51: SI | R51: 46157 | S51: PAGO FACT (REPOSICION DE MERCANCIA)
B52: 46106 | O52: =+Tabla7[[#This Row],[USD]]*Tabla7[[#This Row],[TASA DE CAMBIO]] -> 0 | P52: BANCOS | Q52: SI | R52: 46157 | S52: PAGO FACT (REPOSICION DE MERCANCIA)
B53: 46106 | O53: =+Tabla7[[#This Row],[USD]]*Tabla7[[#This Row],[TASA DE CAMBIO]] -> 0 | P53: BANCOS | Q53: SI | R53: 46157 | S53: PAGO FACT (REPOSICION DE MERCANCIA)
... B55: 46107 | O55: =+Tabla7[[#This Row],[USD]]*Tabla7[[#This Row],[TASA DE CAMBIO]] -> 0 | P55: BANCOS | Q55: SI | R55: 46157 | S55: PAGO FACT (REPOSICION DE MERCANCIA)
B56: 46107 | O56: =+Tabla7[[#This Row],[USD]]*Tabla7[[#This Row],[TASA DE CAMBIO]] -> 0
B57: 46107 | O57: =+Tabla7[[#This Row],[USD]]*Tabla7[[#This Row],[TASA DE CAMBIO]] -> 0
B58: 46107 | O58: =+Tabla7[[#This Row],[USD]]*Tabla7[[#This Row],[TASA DE CAMBIO]] -> 0
B59: 46108 | O59: =+Tabla7[[#This Row],[USD]]*Tabla7[[#This Row],[TASA DE CAMBIO]] -> 0
B60: 46111 | O60: =+Tabla7[[#This Row],[USD]]*Tabla7[[#This Row],[TASA DE CAMBIO]] -> 0
B61: 46112 | O61: =+Tabla7[[#This Row],[USD]]*Tabla7[[#This Row],[TASA DE CAMBIO]] -> 0
O62: =+Tabla7[[#This Row],[USD]]*Tabla7[[#This Row],[TASA DE CAMBIO]] -> 0
O63: =+Tabla7[[#This Row],[USD]]*Tabla7[[#This Row],[TASA DE CAMBIO]] -> 0
O64: =+Tabla7[[#This Row],[USD]]*Tabla7[[#This Row],[TASA DE CAMBIO]] -> 0
N65: 0 | O65: =+Tabla7[[#This Row],[USD]]*Tabla7[[#This Row],[TASA DE CAMBIO]] -> 0
G67: =SUBTOTAL(109,G13:G66) -> 0 | H67: =SUBTOTAL(109,H13:H66) -> 0 | I67: =SUBTOTAL(109,I13:I66) -> 0 | J67: =SUBTOTAL(109,J13:J66) -> 0 | K67: =SUBTOTAL(109,K13:K66) -> 0 | L67: =SUBTOTAL(109,L13:L66) -> 0 | N67: =SUM(N7:N66) -> 238511.68 | O67: =SUM(O7:O66) -> 1.9526647e+08

Sheet GASTOS 
A1: RELACION DE GASTOS
A3: IT | B3: FECHA | C3: PROVEEDOR | D3: CONCEPTO | E3: TIPO DE GASTOS | F3: NOTA DE ENTREGA | G3: Nº FT | H3: Nº CONTROL | I3: EXENTO | J3: BASE IMPONIBLE | K3: IVA | L3: % RET. IVA | M3: RETENCIÓN IVA | N3: A PAGAR | O3: TASA DE CAMBIO | P3: USD | Q3: PAGADO BS | R3: T / P | S3: DEL MES | T3: FECHA PAGO
A4: 1 | B4: 46205 | C4: FAOV | D4: BANAVIH MES MAYO | E4: BANAVIH | K4: =+'GASTOS '!#REF!*0.16 -> #REF! | L4: 0.75 | M4: =+'GASTOS '!#REF!*'GASTOS '!#REF! -> #REF! | N4: 0 | O4: 633.36 | P4: =IFERROR( Tabla8[[#This Row],[PAGADO BS]]/Tabla8[[#This Row],[TASA DE CAMBIO]], 0) -> 14.494127 | Q4: 9180 | R4: BANCOS | T4: 46204
A5: 2 | B5: 46205 | C5: IVSS | D5: SEGURO SOCIAL MES MAYO | E5: IVSS | K5: =+'GASTOS '!$J14*0.16 -> 0 | L5: 0.75 | M5: =+'GASTOS '!$K14*'GASTOS '!$L14 -> 0 | N5: 0 | O5: 633.36 | P5: =IFERROR( Tabla8[[#This Row],[PAGADO BS]]/Tabla8[[#This Row],[TASA DE CAMBIO]], 0) -> 7.1511463 | Q5: 4529.25 | R5: BANCOS | T5: 46204
A6: 3 | B6: 46205 | C6: ALCALDIA DE CARACAS | D6: RETENCIONES MUNICIPALES MES DE JUNIO | E6: RETENCIÓN MUNICIPAL | K6: =+'GASTOS '!$J66*0.16 -> 0 | M6: =+'GASTOS '!$K66*'GASTOS '!$L66 -> #REF! | O6: 633.36 | P6: =IFERROR( Tabla8[[#This Row],[PAGADO BS]]/Tabla8[[#This Row],[TASA DE CAMBIO]], 0) -> 147.48014 | Q6: 93408.02 | R6: BANCOS | T6: 46204
A7: 4 | B7: 46205 | C7: INVERSIONES TORMES | D7: INSUMOS DE LIMPIEZA | E7: MATERIAL DE LIMPIEZA | K7: =+'GASTOS '!#REF!*0.16 -> #REF! | M7: =+'GASTOS '!#REF!*'GASTOS '!#REF! -> #REF! | O7: 633.36 | P7: =IFERROR( Tabla8[[#This Row],[PAGADO BS]]/Tabla8[[#This Row],[TASA DE CAMBIO]], 0) -> 368.49272 | Q7: 233388.55 | R7: BANCOS | T7: 46204
A8: 5 | B8: 46205 | C8: ADMINISTRADORA NAPOLITANO | D8: ALQUILER LOCAL 5 MES DE JULIO | E8: ALQUILERES | K8: =+'GASTOS '!$J19*0.16 -> 0 | L8: 0.75 | M8: =+'GASTOS '!$K19*'GASTOS '!$L19 -> 0 | N8: 0 | O8: 639.7 | P8: =IFERROR( Tabla8[[#This Row],[PAGADO BS]]/Tabla8[[#This Row],[TASA DE CAMBIO]], 0) -> 391.5 | Q8: 250442.55 | R8: BANCOS | T8: 46205
A9: 6 | B9: 46205 | C9: SGSI | D9: HONORARIOS PROFESIONALES MES JULIO | E9: HONORARIOS PROFESIONALES | K9: =+'GASTOS '!$J15*0.16 -> 0 | L9: 0.75 | M9: =+'GASTOS '!$K15*'GASTOS '!$L15 -> 0 | N9: 0 | O9: 639.7 | P9: =IFERROR( Tabla8[[#This Row],[PAGADO BS]]/Tabla8[[#This Row],[TASA DE CAMBIO]], 0) -> 515.57899 | Q9: 329815.88 | R9: BANCOS | T9: 46205
A10: 7 | B10: 46205 | C10: DEEPCOMPANY | D10: PLATAFORMA DIGITAL MES DE JULIO | E10: PLATAFORMA DIGITAL | K10: =+'GASTOS '!$J16*0.16 -> 0 | L10: 0.75 | M10: =+'GASTOS '!$K16*'GASTOS '!$L16 -> 0 | N10: 0 | O10: 639.7 | P10: =IFERROR( Tabla8[[#This Row],[PAGADO BS]]/Tabla8[[#This Row],[TASA DE CAMBIO]], 0) -> 292.81749 | Q10: 187315.35 | R10: BANCOS | T10: 46205
A11: 8 | B11: 46205 | C11: VEHICLE SECURITY | D11: SERVICIO DE SEGURIDAD MES DE JULIO | E11: SERVICIOS DE GPS O SEGURIDAD | O11: 639.7 | P11: =IFERROR( Tabla8[[#This Row],[PAGADO BS]]/Tabla8[[#This Row],[TASA DE CAMBIO]], 0) -> 44.563452 | Q11: 28507.24 | R11: BANCOS | T11: 46205
A12: 9 | B12: 46205 | C12: SERVICIOS EMPRESARIALES NGL | D12: CONTABILIDAD MENSUAL MES DE MAYO | E12: HONORARIOS PROFESIONALES | K12: =+'GASTOS '!$J71*0.16 -> 0 | M12: =+'GASTOS '!$K71*'GASTOS '!$L71 -> 0 | O12: 639.7 | P12: =IFERROR( Tabla8[[#This Row],[PAGADO BS]]/Tabla8[[#This Row],[TASA DE CAMBIO]], 0) -> 643.5 | Q12: 411646.95 | R12: BANCOS | T12: 46205
A13: 10 | B13: 46205 | C13: CORPORACION DIGITEL | D13: SERVICIO TELEFONICO MAYO (VARIAS LINEAS) | E13: DIGITEL | O13: 639.7 | P13: =IFERROR( Tabla8[[#This Row],[PAGADO BS]]/Tabla8[[#This Row],[TASA DE CAMBIO]], 0) -> 125.60974 | Q13: 80352.55 | R13: BANCOS | T13: 46205
A14: 11 | B14: 46205 | C14: MARIA GABRIELA MOLINA (MANGO BAJITO) | D14: COMPRA DE MANTAS (DONACIONES) | E14: DONACIÓN | K14: 0 | L14: 0.75 | M14: =+'GASTOS '!$K4*'GASTOS '!$L4 -> #REF! | N14: 0 | O14: 639.7 | P14: =IFERROR( Tabla8[[#This Row],[PAGADO BS]]/Tabla8[[#This Row],[TASA DE CAMBIO]], 0) -> 719.85851 | Q14: 460493.49 | R14: BANCOS | T14: 46205
A15: 12 | B15: 46205 | C15: - | D15: LAVADO DE PANEL Y ARREGLO PANEL | E15: SERVICIO MTTO DE VEHICULOS | K15: 0 | L15: 0.75 | M15: =+'GASTOS '!$K5*'GASTOS '!$L5 -> 0 | N15: 0 | O15: 639.7 | P15: =IFERROR( Tabla8[[#This Row],[PAGADO BS]]/Tabla8[[#This Row],[TASA DE CAMBIO]], 0) -> 60 | Q15: 38382 | R15: BANCOS | T15: 46205
A16: 13 | B16: 46205 | C16: INCES | D16: 2DO TRIMESTRE 2026 ABRIL - JUNIO | E16: INCES | K16: =+'GASTOS '!$J7*0.16 -> 0 | L16: 0.75 | M16: =+'GASTOS '!$K7*'GASTOS '!$L7 -> #REF! | N16: 0 | O16: 652.97 | P16: =IFERROR( Tabla8[[#This Row],[PAGADO BS]]/Tabla8[[#This Row],[TASA DE CAMBIO]], 0) -> 27.214451 | Q16: 17770.22 | R16: BANCOS | T16: 46206
A17: 14 | B17: 46205 | C17: TIENDA | D17: GASTOS DE SEGURIDAD | E17: SEGURIDAD | K17: =+'GASTOS '!$J91*0.16 -> 0 | M17: =+'GASTOS '!$K91*'GASTOS '!$L91 -> 0 | O17: 652.97 | P17: =IFERROR( Tabla8[[#This Row],[PAGADO BS]]/Tabla8[[#This Row],[TASA DE CAMBIO]], 0) -> 50 | Q17: =50*Tabla8[[#This Row],[TASA DE CAMBIO]] -> 32648.5 | R17: CAJA ADMON | T17: 46205
A18: 15 | B18: 46206 | C18: TRABAJADORES | D18: BONO DE ALIMENTACION MES DE JUNIO | E18: BONO ALIMENTACION | K18: =+'GASTOS '!$J6*0.16 -> 0 | L18: 0.75 | M18: =+'GASTOS '!$K6*'GASTOS '!$L6 -> 0 | N18: 0 | O18: 652.97 | P18: =IFERROR( Tabla8[[#This Row],[PAGADO BS]]/Tabla8[[#This Row],[TASA DE CAMBIO]], 0) -> 1518.7244 | Q18: 991681.48 | R18: BANCOS | T18: 46206
A19: 16 | B19: 46206 | C19: CORPO INDUSTRI | D19: COMPRA (40) BULTOS DE AGUA (DONACIONES) | E19: DONACIÓN | K19: =+'GASTOS '!$J8*0.16 -> 0 | L19: 0.75 | M19: =+'GASTOS '!$K8*'GASTOS '!$L8 -> 0 | N19: 0 | O19: 652.97 | P19: =IFERROR( Tabla8[[#This Row],[PAGADO BS]]/Tabla8[[#This Row],[TASA DE CAMBIO]], 0) -> 359.60018 | Q19: 234808.13 | R19: BANCOS | T19: 46206
A20: 17 | B20: 46206 | C20: BANCO DE VENEZUELA | D20: COMISION LINEA DE CREDITO 2 | E20: PRESTAMO BANCARIO | K20: =+'GASTOS '!$J9*0.16 -> 0 | L20: 0.75 | M20: =+'GASTOS '!$K9*'GASTOS '!$L9 -> 0 | N20: 0 | O20: 652.97 | P20: =IFERROR( Tabla8[[#This Row],[PAGADO BS]]/Tabla8[[#This Row],[TASA DE CAMBIO]], 0) -> 516.27491 | Q20: 337112.03 | R20: BANCOS | T20: 46206
A21: 18 | B21: 46208 | C21: BANCO DE VENEZUELA | D21: CREDITO BANCARIO Nº 2 CUOTA Nº 10 | E21: PRESTAMO BANCARIO | K21: =+'GASTOS '!$J10*0.16 -> 0 | L21: 0.75 | M21: =+'GASTOS '!$K10*'GASTOS '!$L10 -> 0 | N21: 0 | O21: 652.97 | P21: =IFERROR( Tabla8[[#This Row],[PAGADO BS]]/Tabla8[[#This Row],[TASA DE CAMBIO]], 0) -> 11042.547 | Q21: 7210451.8 | R21: BANCOS | T21: 46208
A22: 19 | B22: 46209 | C22: GLOBAL IT SYSTEM (SR. RENE) | D22: COMBUSTIBLE SEMANA DEL 06/07/2026 AL 10/07/2026 | E22: GASOLINA | K22: =+'GASTOS '!$J11*0.16 -> 0 | L22: 0.75 | M22: =+'GASTOS '!$K11*'GASTOS '!$L11 -> 0 | N22: 0 | O22: 667.05 | P22: =IFERROR( Tabla8[[#This Row],[PAGADO BS]]/Tabla8[[#This Row],[TASA DE CAMBIO]], 0) -> 20 | Q22: 13341 | R22: BANCOS | T22: 46209
A23: 20 | B23: 46210 | C23: SENIAT | D23: RETENCIONES DE ISLR MES JUNIO | E23: RETENCION ISLR | K23: =+'GASTOS '!$J13*0.16 -> 0 | L23: 0.75 | M23: =+'GASTOS '!$K13*'GASTOS '!$L13 -> 0 | N23: 0 | O23: 674.93 | P23: =IFERROR( Tabla8[[#This Row],[PAGADO BS]]/Tabla8[[#This Row],[TASA DE CAMBIO]], 0) -> 142.33669 | Q23: 96067.3 | R23: BANCOS | T23: 46210
A24: 21 | B24: 46210 | C24: SENIAT | D24: IGTF 2DA QNA JUNIO | E24: IGTF | K24: =+'GASTOS '!$J56*0.16 -> 0 | M24: =+'GASTOS '!$K56*'GASTOS '!$L56 -> 0 | O24: 674.93 | P24: =IFERROR( Tabla8[[#This Row],[PAGADO BS]]/Tabla8[[#This Row],[TASA DE CAMBIO]], 0) -> 0.5240099 | Q24: 353.67 | R24: BANCOS | T24: 46210
A25: 22 | B25: 46211 | C25: ALCALDIA DE CARACAS | D25: PATENTE TIENDA MES JUNIO | E25: IAE (ALCALDIA) | K25: =+'GASTOS '!$J12*0.16 -> 0 | L25: 0.75 | M25: =+'GASTOS '!$K12*'GASTOS '!$L12 -> 0 | N25: 0 | O25: 674.93 | P25: =IFERROR( Tabla8[[#This Row],[PAGADO BS]]/Tabla8[[#This Row],[TASA DE CAMBIO]], 0) -> 6418.4906 | Q25: 4332031.9 | R25: BANCOS | T25: 46210
A26: 23 | B26: 46212 | C26: TELECOMUNICACIONES SILVERDATA | D26: INTERNET TIENDA MES DE JULIO | E26: INTERNET | K26: =+'GASTOS '!$J61*0.16 -> 0 | M26: =+'GASTOS '!$K61*'GASTOS '!$L61 -> 0 | O26: 674.93 | P26: =IFERROR( Tabla8[[#This Row],[PAGADO BS]]/Tabla8[[#This Row],[TASA DE CAMBIO]], 0) -> 86.896863 | Q26: 58649.3 | R26: BANCOS | T26: 46210
A27: 24 | B27: 46212 | C27: MDS TELECOM | D27: INTERNET TIENDA Y SALA DE CAPACITACION MES DE JULIO | E27: INTERNET | K27: =+'GASTOS '!#REF!*0.16 -> #REF! | L27: 0.75 | M27: =+'GASTOS '!#REF!*'GASTOS '!#REF! -> #REF! | N27: 0 | O27: 674.93 | P27: =IFERROR( Tabla8[[#This Row],[PAGADO BS]]/Tabla8[[#This Row],[TASA DE CAMBIO]], 0) -> 180.25863 | Q27: 121661.96 | R27: BANCOS | T27: 46210
A28: 25 | B28: 46212 | C28: INVERSIONES MAXILOPEZ | D28: COMPRA CAFÉ / AZUCAR / AGUA | E28: CAFÉ AZUCAR OTROS | K28: =+'GASTOS '!#REF!*0.16 -> #REF! | L28: 0.75 | M28: 0 | N28: 0 | O28: 674.93 | P28: =IFERROR( Tabla8[[#This Row],[PAGADO BS]]/Tabla8[[#This Row],[TASA DE CAMBIO]], 0) -> 330.89989 | Q28: 223334.26 | R28: BANCOS | T28: 46210
A29: 26 | B29: 46212 | C29: WINTERPLAS | D29: SERVILLETAS | E29: MATERIAL DE OFICINA | K29: =+'GASTOS '!$J17*0.16 -> 0 | L29: 0.75 | M29: =+'GASTOS '!$K17*'GASTOS '!$L17 -> 0 | N29: 0 | O29: 674.93 | P29: =IFERROR( Tabla8[[#This Row],[PAGADO BS]]/Tabla8[[#This Row],[TASA DE CAMBIO]], 0) -> 19.752048 | Q29: 13331.25 | R29: BANCOS | T29: 46210
A30: 27 | B30: 46212 | C30: CANTV | D30: SERVICIO TELEFONICO 0212-6683946 | E30: CANTV | K30: =+'GASTOS '!$J18*0.16 -> 0 | L30: 0.75 | M30: =+'GASTOS '!$K18*'GASTOS '!$L18 -> 0 | N30: 0 | O30: 685.94 | P30: =IFERROR( Tabla8[[#This Row],[PAGADO BS]]/Tabla8[[#This Row],[TASA DE CAMBIO]], 0) -> 22.450025 | Q30: 15399.37 | R30: BANCOS | T30: 46211
A31: 28 | B31: 46212 | C31: HIDROCAPITAL | D31: SERVICIO DE AGUA TIENDA MES DE JUNIO | E31: HIDROCAPITAL | K31: =+'GASTOS '!#REF!*0.16 -> #REF! | L31: 0.75 | M31: =+'GASTOS '!#REF!*'GASTOS '!#REF! -> #REF! | N31: 0 | O31: 685.94 | P31: =IFERROR( Tabla8[[#This Row],[PAGADO BS]]/Tabla8[[#This Row],[TASA DE CAMBIO]], 0) -> 104.61625 | Q31: 71760.47 | R31: BANCOS | T31: 46211
A32: 29 | B32: 46212 | C32: ALCALDIA DE CARACAS | D32: ASEO URBANO MES JULIO | E32: ASEO URBANO | K32: =+'GASTOS '!$J20*0.16 -> 0 | L32: 0.75 | M32: =+'GASTOS '!$K20*'GASTOS '!$L20 -> 0 | N32: 0 | O32: 685.94 | P32: =IFERROR( Tabla8[[#This Row],[PAGADO BS]]/Tabla8[[#This Row],[TASA DE CAMBIO]], 0) -> 28.313278 | Q32: 19421.21 | R32: BANCOS | T32: 46211
A33: 30 | B33: 46212 | C33: ADMINISTRADORA NAPOLITANO | D33: ALQUILER LOCAL 1 2 Y 3 MES JULIO | E33: ALQUILERES | K33: =+'GASTOS '!$J21*0.16 -> 0 | L33: 0.75 | M33: =+'GASTOS '!$K21*'GASTOS '!$L21 -> 0 | N33: 0 | O33: 685.94 | P33: =IFERROR( Tabla8[[#This Row],[PAGADO BS]]/Tabla8[[#This Row],[TASA DE CAMBIO]], 0) -> 1798.125 | Q33: 1233405.9 | R33: BANCOS | T33: 46211
A34: 31 | B34: 46212 | C34: CORPORACION PARK | D34: ALQUILER DE ESTACIONAMIENTO TORRE AMERICA JULIO | E34: ALQUILERES | K34: =+'GASTOS '!$J22*0.16 -> 0 | L34: 0.75 | M34: =+'GASTOS '!$K22*'GASTOS '!$L22 -> 0 | N34: 0 | O34: 685.94 | P34: =IFERROR( Tabla8[[#This Row],[PAGADO BS]]/Tabla8[[#This Row],[TASA DE CAMBIO]], 0) -> 83.087486 | Q34: 56993.03 | R34: BANCOS | T34: 46211
A35: 32 | B35: 46212 | C35: CASHEA | D35: PLATAFORMA DIGITALES MES JUNIO | E35: PLATAFORMA DIGITAL | K35: =+'GASTOS '!$J24*0.16 -> 0 | L35: 0.75 | M35: =+'GASTOS '!$K24*'GASTOS '!$L24 -> 0 | N35: 0 | O35: 700.22 | P35: =IFERROR( Tabla8[[#This Row],[PAGADO BS]]/Tabla8[[#This Row],[TASA DE CAMBIO]], 0) -> 333.69 | Q35: 233656.41 | R35: BANCOS | T35: 46212
A36: 33 | B36: 46212 | C36: - | D36: AISLANTE TERMICO PARA TRANSPOTE (PANEL) | E36: GASTOS OPERATIVOS | K36: =+'GASTOS '!$J26*0.16 -> 0 | M36: =+'GASTOS '!$K26*'GASTOS '!$L26 -> 0 | O36: 700.22 | P36: =IFERROR( Tabla8[[#This Row],[PAGADO BS]]/Tabla8[[#This Row],[TASA DE CAMBIO]], 0) -> 43.154994 | Q36: 30217.99 | R36: BANCOS | T36: 46212
A37: 34 | B37: 46212 | C37: SAN DIEGO | D37: CONDOMINIO SAN DIEGO (TIENDA) MES JUNIO | E37: ALQUILERES | K37: =+'GASTOS '!$J68*0.16 -> 0 | M37: =+'GASTOS '!$K68*'GASTOS '!$L68 -> 0 | O37: 700.22 | P37: =IFERROR( Tabla8[[#This Row],[PAGADO BS]]/Tabla8[[#This Row],[TASA DE CAMBIO]], 0) -> 16.52145 | Q37: 11568.65 | R37: BANCOS | T37: 46212
A38: 35 | B38: 46212 | C38: TIENDA | D38: GASTOS DE SEGURIDAD | E38: SEGURIDAD | K38: =+'GASTOS '!$J92*0.16 -> 0 | M38: =+'GASTOS '!$K92*'GASTOS '!$L92 -> 0 | O38: 700.22 | P38: =IFERROR( Tabla8[[#This Row],[PAGADO BS]]/Tabla8[[#This Row],[TASA DE CAMBIO]], 0) -> 50 | Q38: =50*700.22 -> 35011 | R38: CAJA ADMON | T38: 46212
A39: 36 | B39: 46212 | C39: TIENDA | D39: PAGO ALQUILER ESTACIONAMIENTO DE TIENDA | E39: SEGURIDAD | K39: =+'GASTOS '!$J93*0.16 -> 0 | M39: =+'GASTOS '!$K93*'GASTOS '!$L93 -> 0 | O39: 700.22 | P39: =IFERROR( Tabla8[[#This Row],[PAGADO BS]]/Tabla8[[#This Row],[TASA DE CAMBIO]], 0) -> 90 | Q39: =90*700.22 -> 63019.8 | R39: CAJA ADMON | T39: 46212
A40: 37 | B40: 46217 | C40: SENIAT | D40: DECLARACION DE IVA 2DA QNA JUNIO | E40: IVA | K40: =+'GASTOS '!$J28*0.16 -> 0 | M40: =+'GASTOS '!$K28*'GASTOS '!$L28 -> #REF! | O40: 724 | P40: =IFERROR( Tabla8[[#This Row],[PAGADO BS]]/Tabla8[[#This Row],[TASA DE CAMBIO]], 0) -> 2287.6603 | Q40: 1656266.1 | R40: BANCOS | T40: 46217
A41: 38 | B41: 46217 | C41: SENIAT | D41: RETENCION IVA (PROVEEDORES) 2DA QNA JUNIO | E41: RETENCIÓN IVA | K41: =+'GASTOS '!$J29*0.16 -> 0 | L41: 0.75 | M41: =+'GASTOS '!$K29*'GASTOS '!$L29 -> 0 | N41: 0 | O41: 724 | P41: =IFERROR( Tabla8[[#This Row],[PAGADO BS]]/Tabla8[[#This Row],[TASA DE CAMBIO]], 0) -> 2465.3758 | Q41: 1784932.1 | R41: BANCOS | T41: 46217
A42: 39 | B42: 46217 | C42: SENIAT | D42: ANTICIPO ISLR 2DA QNA JUNIO | E42: ISLR ANTICIPADO | K42: =+'GASTOS '!$J30*0.16 -> 0 | L42: 0.75 | M42: =+'GASTOS '!$K30*'GASTOS '!$L30 -> 0 | N42: 0 | O42: 724 | P42: =IFERROR( Tabla8[[#This Row],[PAGADO BS]]/Tabla8[[#This Row],[TASA DE CAMBIO]], 0) -> 878.40837 | Q42: 635967.66 | R42: BANCOS | T42: 46217
A43: 40 | B43: 46217 | C43: GLOBAL IT SYSTEM (SR. RENE) | D43: COMBUSTIBLE SEMANA DEL 13/07/2026 AL 16/07/2026 | E43: GASOLINA | K43: =+'GASTOS '!#REF!*0.16 -> #REF! | L43: 0.75 | M43: =+'GASTOS '!#REF!*'GASTOS '!#REF! -> #REF! | N43: 0 | O43: 724 | P43: =IFERROR( Tabla8[[#This Row],[PAGADO BS]]/Tabla8[[#This Row],[TASA DE CAMBIO]], 0) -> 20 | Q43: 14480 | R43: BANCOS | T43: 46217
A44: 41 | B44: 46217 | C44: MST TECHNOLOGIES | D44: PLATAFORMA DIGITAL MES JUNIO | E44: PLATAFORMA DIGITAL | K44: =+'GASTOS '!#REF!*0.16 -> #REF! | L44: 0.75 | M44: =+'GASTOS '!#REF!*'GASTOS '!#REF! -> #REF! | N44: 0 | O44: 724 | P44: =IFERROR( Tabla8[[#This Row],[PAGADO BS]]/Tabla8[[#This Row],[TASA DE CAMBIO]], 0) -> 100.28935 | Q44: 72609.49 | R44: BANCOS | T44: 46217
A45: 42 | B45: 46218 | C45: SIDCAI | D45: ANTICIPO LOCTI MES JUNIO 2026 | E45: LOCTI | K45: =+'GASTOS '!$J32*0.16 -> 0 | L45: 0.75 | M45: =+'GASTOS '!$K32*'GASTOS '!$L32 -> 0 | N45: 0 | O45: 724 | P45: =IFERROR( Tabla8[[#This Row],[PAGADO BS]]/Tabla8[[#This Row],[TASA DE CAMBIO]], 0) -> 274.45862 | Q45: 198708.04 | R45: BANCOS | T45: 46217
A46: 43 | B46: 46218 | C46: TRABAJADORES | D46: NOMINA 1ERA QNA JULIO | E46: NOMINA | O46: 725.75 | P46: =IFERROR( Tabla8[[#This Row],[PAGADO BS]]/Tabla8[[#This Row],[TASA DE CAMBIO]], 0) -> 210.8164 | Q46: 153000 | R46: BANCOS | T46: 46218
A47: 44 | B47: 46218 | C47: TRABAJADORES | D47: COMPLEMENTO DE ALIMENTACION 1ERA QNA JULIO | E47: COMPLEMENTO BONO ALIMENTACION | K47: =+'GASTOS '!#REF!*0.16 -> #REF! | L47: 0.75 | M47: =+'GASTOS '!#REF!*'GASTOS '!#REF! -> #REF! | N47: 0 | O47: 725.75 | P47: =IFERROR( Tabla8[[#This Row],[PAGADO BS]]/Tabla8[[#This Row],[TASA DE CAMBIO]], 0) -> 4563.0579 | Q47: 3311639.3 | R47: BANCOS | T47: 46218
A48: 45 | B48: 46218 | C48: SEGURO CARACAS | D48: SEGURO CARACAS (MOTO) | E48: SEGUROS | K48: =+'GASTOS '!$J59*0.16 -> 0 | M48: =+'GASTOS '!$K59*'GASTOS '!$L59 -> 0 | O48: 732.48 | P48: =IFERROR( Tabla8[[#This Row],[PAGADO BS]]/Tabla8[[#This Row],[TASA DE CAMBIO]], 0) -> 43.830002 | Q48: 32104.6 | R48: BANCOS | T48: 46220
A49: 46 | B49: 46219 | C49: - | D49: INSTALACION DE AISLANTE TERMICO PARA PANEL | E49: SERVICIO MTTO DE VEHICULOS | K49: =+'GASTOS '!$J27*0.16 -> 0 | L49: 0.75 | M49: =+'GASTOS '!$K27*'GASTOS '!$L27 -> #REF! | N49: 0 | O49: 737.88 | P49: =IFERROR( Tabla8[[#This Row],[PAGADO BS]]/Tabla8[[#This Row],[TASA DE CAMBIO]], 0) -> 80 | Q49: 59030.4 | R49: BANCOS | T49: 46216
A50: 47 | B50: 46219 | C50: CANTV | D50: SERVICIO TELEFONICO (0212-761.64.24) | E50: CANTV | K50: =+'GASTOS '!$J31*0.16 -> 0 | L50: 0.75 | M50: =+'GASTOS '!$K31*'GASTOS '!$L31 -> #REF! | N50: 0 | O50: 724 | P50: =IFERROR( Tabla8[[#This Row],[PAGADO BS]]/Tabla8[[#This Row],[TASA DE CAMBIO]], 0) -> 9.5287017 | Q50: 6898.78 | R50: BANCOS | T50: 46217
A51: 48 | B51: 46219 | C51: CORPOELEC | D51: ELECTRICIDAD/RELLENO SANITARIO / ASEO LOCAL 5 | E51: ELECTRICIDAD | K51: =+'GASTOS '!$J36*0.16 -> 0 | L51: 0.75 | M51: =+'GASTOS '!$K36*'GASTOS '!$L36 -> 0 | N51: 0 | O51: 724 | P51: =IFERROR( Tabla8[[#This Row],[PAGADO BS]]/Tabla8[[#This Row],[TASA DE CAMBIO]], 0) -> 62.725691 | Q51: 45413.4 | R51: BANCOS | T51: 46217
A52: 49 | B52: 46219 | C52: IP NET | D52: INTERNET OFICINA MES DE JULIO | E52: INTERNET | K52: =+'GASTOS '!#REF!*0.16 -> #REF! | L52: 0.75 | M52: =+'GASTOS '!#REF!*'GASTOS '!#REF! -> #REF! | N52: 0 | O52: 724 | P52: =IFERROR( Tabla8[[#This Row],[PAGADO BS]]/Tabla8[[#This Row],[TASA DE CAMBIO]], 0) -> 121.37982 | Q52: 87878.99 | R52: BANCOS | T52: 46217
A53: 50 | B53: 46219 | C53: - | D53: GESTION LICENCIA CONDUCTOR PARA PANEL | E53: OTROS GASTOS | K53: =+'GASTOS '!$J37*0.16 -> 0 | L53: 0.75 | M53: =+'GASTOS '!$K37*'GASTOS '!$L37 -> 0 | N53: 0 | O53: 724 | P53: =IFERROR( Tabla8[[#This Row],[PAGADO BS]]/Tabla8[[#This Row],[TASA DE CAMBIO]], 0) -> 69.61326 | Q53: 50400 | R53: BANCOS | T53: 46217
A54: 51 | B54: 46219 | C54: MERCADO LIBRE | D54: PLATAFORMA DIGITAL MES JUNIO | E54: PLATAFORMA DIGITAL | K54: =+'GASTOS '!#REF!*0.16 -> #REF! | L54: 0.75 | M54: =+'GASTOS '!#REF!*'GASTOS '!#REF! -> #REF! | N54: 0 | O54: 725.75 | P54: =IFERROR( Tabla8[[#This Row],[PAGADO BS]]/Tabla8[[#This Row],[TASA DE CAMBIO]], 0) -> 4443.7811 | Q54: 3225074.1 | R54: BANCOS | T54: 46218
A55: 52 | B55: 46219 | C55: - | D55: COMPRA E INSTALACION DE SILENCIADOR PARA PANEL / FILTRO | E55: SERVICIO MTTO DE VEHICULOS | K55: =+'GASTOS '!$J69*0.16 -> 0 | M55: =+'GASTOS '!$K69*'GASTOS '!$L69 -> #REF! | O55: 725.75 | P55: =IFERROR( Tabla8[[#This Row],[PAGADO BS]]/Tabla8[[#This Row],[TASA DE CAMBIO]], 0) -> 175 | Q55: 127006.25 | R55: BANCOS | T55: 46218
A56: 53 | B56: 46219 | C56: - | D56: PLANILLA PERMISO DE TRASLADO PANEL + GESTION PERMISO DE TRASLADO DE PANEL 50% (TASA EURO) | E56: PERMISOLOGIA | K56: =+'GASTOS '!$J42*0.16 -> 0 | M56: =+'GASTOS '!$K42*'GASTOS '!$L42 -> 0 | O56: 725.75 | P56: =IFERROR( Tabla8[[#This Row],[PAGADO BS]]/Tabla8[[#This Row],[TASA DE CAMBIO]], 0) -> 309.37857 | Q56: 224531.5 | R56: BANCOS | T56: 46218
A57: 54 | B57: 46219 | C57: - | D57: ACEITES PARA CAMBIO DE PANEL | E57: SERVICIO MTTO DE VEHICULOS | K57: =+'GASTOS '!$J43*0.16 -> 0 | L57: 0.75 | M57: =+'GASTOS '!$K43*'GASTOS '!$L43 -> #REF! | N57: 0 | O57: 725.75 | P57: =IFERROR( Tabla8[[#This Row],[PAGADO BS]]/Tabla8[[#This Row],[TASA DE CAMBIO]], 0) -> 49.919311 | Q57: 36228.94 | R57: BANCOS | T57: 46218
A58: 55 | B58: 46219 | C58: SERVICIO NACIONAL DE CONTRATACIONES | D58: TASA POR ACTUALIZACION DE REGISTRO RNC 2026 (ANUAL) | E58: PERMISOLOGIA | K58: =+'GASTOS '!#REF!*0.16 -> #REF! | L58: 0.75 | M58: =+'GASTOS '!#REF!*'GASTOS '!#REF! -> #REF! | N58: 0 | O58: 727.45 | P58: =IFERROR( Tabla8[[#This Row],[PAGADO BS]]/Tabla8[[#This Row],[TASA DE CAMBIO]], 0) -> 153.60891 | Q58: 111742.8 | R58: BANCOS | T58: 46219
A59: 56 | B59: 46219 | C59: - | D59: GESTION PERMISO DE TRASLADO DE PANEL DIFERENCIA 50% (TASA EURO) | E59: PERMISOLOGIA | K59: =+'GASTOS '!$J45*0.16 -> 0 | L59: 0.75 | M59: =+'GASTOS '!$K45*'GASTOS '!$L45 -> 0 | N59: 0 | O59: 727.45 | P59: =IFERROR( Tabla8[[#This Row],[PAGADO BS]]/Tabla8[[#This Row],[TASA DE CAMBIO]], 0) -> 57.603272 | Q59: 41903.5 | R59: BANCOS | T59: 46220
A60: 57 | B60: 46219 | C60: CORPOELEC | D60: ELECTRICIDAD/RELLENO SANITARIO / TIENDA JUNIO | E60: ELECTRICIDAD | O60: 742.23 | P60: =IFERROR( Tabla8[[#This Row],[PAGADO BS]]/Tabla8[[#This Row],[TASA DE CAMBIO]], 0) -> 117.35251 | Q60: 87102.55 | R60: BANCOS | T60: 46227
A61: 58 | B61: 46219 | C61: TIENDA | D61: GASTOS DE SEGURIDAD | E61: SEGURIDAD | K61: =+'GASTOS '!$J94*0.16 -> 0 | M61: =+'GASTOS '!$K94*'GASTOS '!$L94 -> 0 | O61: 742.23 | P61: =IFERROR( Tabla8[[#This Row],[PAGADO BS]]/Tabla8[[#This Row],[TASA DE CAMBIO]], 0) -> 50 | Q61: =50*742.23 -> 37111.5 | R61: CAJA ADMON | T61: 46219
A62: 59 | B62: 46220 | C62: DYNAMIC TECNOLOGIA | D62: CARGADOR DUAL SOPORTE TECNICO | E62: OTROS GASTOS | K62: =+'GASTOS '!$J47*0.16 -> 0 | L62: 0.75 | M62: =+'GASTOS '!$K47*'GASTOS '!$L47 -> #REF! | N62: 0 | O62: 732.48 | P62: =IFERROR( Tabla8[[#This Row],[PAGADO BS]]/Tabla8[[#This Row],[TASA DE CAMBIO]], 0) -> 67.59446 | Q62: 49511.59 | R62: BANCOS | T62: 46220
A63: 60 | B63: 46220 | C63: LOS INTOCABLES | D63: CAMBIO DE ACEITE PANEL (MANO DE OBRA) | E63: SERVICIO MTTO DE VEHICULOS | K63: =+'GASTOS '!$J52*0.16 -> 0 | M63: =+'GASTOS '!$K52*'GASTOS '!$L52 -> #REF! | O63: 732.48 | P63: =IFERROR( Tabla8[[#This Row],[PAGADO BS]]/Tabla8[[#This Row],[TASA DE CAMBIO]], 0) -> 14.999863 | Q63: 10987.1 | R63: BANCOS | T63: 46220
A64: 61 | B64: 46220 | C64: DYNAMIC TECNOLOGIA | D64: ADAPTADOR MARKETING | E64: MARKETING GASTOS | K64: =+'GASTOS '!$J53*0.16 -> 0 | M64: =+'GASTOS '!$K53*'GASTOS '!$L53 -> 0 | O64: 732.48 | P64: =IFERROR( Tabla8[[#This Row],[PAGADO BS]]/Tabla8[[#This Row],[TASA DE CAMBIO]], 0) -> 15.078787 | Q64: 11044.91 | R64: BANCOS | T64: 46220
A65: 62 | B65: 46225 | C65: MEGA SOFT | D65: PLATAFORMA DIGITAL SERVICIO MES JUNIO | E65: PLATAFORMA DIGITAL | K65: =+'GASTOS '!#REF!*0.16 -> #REF! | M65: =+'GASTOS '!#REF!*'GASTOS '!#REF! -> #REF! | O65: 737.23 | P65: =IFERROR( Tabla8[[#This Row],[PAGADO BS]]/Tabla8[[#This Row],[TASA DE CAMBIO]], 0) -> 58.854347 | Q65: 43389.19 | R65: BANCOS | T65: 46224
A66: 63 | B66: 46225 | D66: CERTIFICADO MEDICO CONDUCTOR | E66: PERMISOLOGIA | K66: =+'GASTOS '!#REF!*0.16 -> #REF! | M66: =+'GASTOS '!#REF!*'GASTOS '!#REF! -> #REF! | O66: 737.23 | P66: =IFERROR( Tabla8[[#This Row],[PAGADO BS]]/Tabla8[[#This Row],[TASA DE CAMBIO]], 0) -> 19.991861 | Q66: 14738.6 | R66: BANCOS | T66: 46224
A67: 64 | B67: 46225 | C67: SUMINISTROS PLASTICOS CARIBE | D67: ENVOPLAST NEGROS PARA ENVIOS + BOLSAS | E67: GASTOS DE ENVÍO | K67: =+'GASTOS '!$J58*0.16 -> 0 | M67: =+'GASTOS '!$K58*'GASTOS '!$L58 -> #REF! | O67: 737.23 | P67: =IFERROR( Tabla8[[#This Row],[PAGADO BS]]/Tabla8[[#This Row],[TASA DE CAMBIO]], 0) -> 383.14999 | Q67: 282469.67 | R67: BANCOS | T67: 46225
A68: 65 | B68: 46225 | C68: VENSPEED | D68: TIRROS POR 3 CAJAS | E68: GASTOS DE ENVÍO | K68: =+'GASTOS '!$J54*0.16 -> 0 | M68: =+'GASTOS '!$K54*'GASTOS '!$L54 -> #REF! | O68: 737.23 | P68: =IFERROR( Tabla8[[#This Row],[PAGADO BS]]/Tabla8[[#This Row],[TASA DE CAMBIO]], 0) -> 251.7528 | Q68: 185599.72 | R68: BANCOS | T68: 46225
A69: 66 | B69: 46225 | C69: ETIQWORLDS | D69: ROLLITOS DE ETIQUETAS + DELIVERY | E69: GASTOS DE ENVÍO | K69: =+'GASTOS '!#REF!*0.16 -> #REF! | M69: =+'GASTOS '!#REF!*'GASTOS '!#REF! -> #REF! | O69: 737.23 | P69: =IFERROR( Tabla8[[#This Row],[PAGADO BS]]/Tabla8[[#This Row],[TASA DE CAMBIO]], 0) -> 182.75042 | Q69: 134729.09 | R69: BANCOS | T69: 46225
A70: 67 | B70: 46225 | D70: ROLLOS TERMICOS | E70: OTROS GASTOS ADMINISTRATIVOS | K70: =+'GASTOS '!$J56*0.16 -> 0 | M70: =+'GASTOS '!$K56*'GASTOS '!$L56 -> 0 | O70: 737.88 | P70: =IFERROR( Tabla8[[#This Row],[PAGADO BS]]/Tabla8[[#This Row],[TASA DE CAMBIO]], 0) -> 178 | Q70: 131342.64 | R70: BANCOS | T70: 46226
A71: 68 | B71: 46225 | C71: ITBM | D71: PLATAFORMA DIGITAL MES JULIO | E71: PLATAFORMA DIGITAL | O71: 742.23 | P71: =IFERROR( Tabla8[[#This Row],[PAGADO BS]]/Tabla8[[#This Row],[TASA DE CAMBIO]], 0) -> 140 | Q71: 103912.2 | R71: BANCOS | T71: 46227
A72: 69 | B72: 46226 | C72: JESUS BOLIVAR | D72: PAGO DE LIQUIDACION | E72: LIQUIDACIONES (PERSONAL) | K72: =+'GASTOS '!$J74*0.16 -> 0 | M72: =+'GASTOS '!$K74*'GASTOS '!$L74 -> #REF! | O72: 737.88 | P72: =IFERROR( Tabla8[[#This Row],[PAGADO BS]]/Tabla8[[#This Row],[TASA DE CAMBIO]], 0) -> 56.042392 | Q72: 41352.56 | R72: BANCOS | T72: 46226
A73: 70 | B73: 46232 | C73: COMPRAS | D73: DIF GASTO MTTO MTO REINTEGRO JUAN MARQUEZ | E73: SEGUROS | K73: =+'GASTOS '!$J49*0.16 -> 0 | M73: =+'GASTOS '!$K49*'GASTOS '!$L49 -> 0 | O73: 744.22 | P73: =IFERROR( Tabla8[[#This Row],[PAGADO BS]]/Tabla8[[#This Row],[TASA DE CAMBIO]], 0) -> 5.5524039 | Q73: 4132.21 | R73: BANCOS | T73: 46232
A74: 71 | B74: 46232 | C74: COMPRAS | D74: DIF GASOLINA PANEL | E74: GASOLINA | K74: =+'GASTOS '!#REF!*0.16 -> #REF! | M74: =+'GASTOS '!#REF!*'GASTOS '!#REF! -> #REF! | O74: 744.22 | P74: =IFERROR( Tabla8[[#This Row],[PAGADO BS]]/Tabla8[[#This Row],[TASA DE CAMBIO]], 0) -> 2.6873774 | Q74: 2000 | R74: BANCOS | T74: 46232
A75: 72 | B75: 46232 | C75: BANCO DE VENEZUELA | D75: CREDITO BANCARIO Nº 3 CUOTA Nº 08 | E75: PRESTAMO BANCARIO | K75: =+'GASTOS '!$J75*0.16 -> 0 | M75: =+'GASTOS '!$K75*'GASTOS '!$L75 -> 0 | O75: 744.22 | P75: =IFERROR( Tabla8[[#This Row],[PAGADO BS]]/Tabla8[[#This Row],[TASA DE CAMBIO]], 0) -> 9757.641 | Q75: 7261831.6 | R75: BANCOS | T75: 46232
A76: 73 | B76: 46232 | C76: SERVICIOS EMPRESARIALES NGL | D76: CONTABILIDAD MENSUAL MES DE JUNIO | E76: HONORARIOS PROFESIONALES | K76: =+'GASTOS '!$J76*0.16 -> 0 | M76: =+'GASTOS '!$K76*'GASTOS '!$L76 -> 0 | O76: 744.22 | P76: =IFERROR( Tabla8[[#This Row],[PAGADO BS]]/Tabla8[[#This Row],[TASA DE CAMBIO]], 0) -> 643.50864 | Q76: 478912 | R76: BANCOS | T76: 46232
A77: 74 | B77: 46233 | C77: COMPRAS | D77: LAVADO DE MOTO | E77: SERVICIO MTTO DE VEHICULOS | O77: 742.81 | P77: =IFERROR( Tabla8[[#This Row],[PAGADO BS]]/Tabla8[[#This Row],[TASA DE CAMBIO]], 0) -> 5 | Q77: 3714.05 | R77: BANCOS | T77: 46231
A78: 75 | B78: 46233 | C78: COMPRAS | D78: CAMBIO DE ACEITE MOTO | E78: SERVICIO MTTO DE VEHICULOS | K78: =+'GASTOS '!$J57*0.16 -> 0 | M78: =+'GASTOS '!$K57*'GASTOS '!$L57 -> 0 | O78: 742.81 | P78: =IFERROR( Tabla8[[#This Row],[PAGADO BS]]/Tabla8[[#This Row],[TASA DE CAMBIO]], 0) -> 25 | Q78: 18570.25 | R78: BANCOS | T78: 46231
A79: 76 | B79: 46233 | C79: COMPRAS | D79: FRENOS MOTO | E79: SERVICIO MTTO DE VEHICULOS | K79: =+'GASTOS '!#REF!*0.16 -> #REF! | M79: =+'GASTOS '!#REF!*'GASTOS '!#REF! -> #REF! | O79: 742.81 | P79: =IFERROR( Tabla8[[#This Row],[PAGADO BS]]/Tabla8[[#This Row],[TASA DE CAMBIO]], 0) -> 30 | Q79: 22284.3 | R79: BANCOS | T79: 46231
A80: 77 | B80: 46233 | C80: COMPRAS | D80: CAJA DE MASCARILLAS (TIENDA-TORRE) | E80: OTROS GASTOS | K80: =+'GASTOS '!$J70*0.16 -> 0 | M80: =+'GASTOS '!$K70*'GASTOS '!$L70 -> 0 | O80: 742.81 | P80: =IFERROR( Tabla8[[#This Row],[PAGADO BS]]/Tabla8[[#This Row],[TASA DE CAMBIO]], 0) -> 20 | Q80: 14856.2 | R80: BANCOS | T80: 46231
A81: 78 | B81: 46233 | C81: SENIAT | D81: ANTICIPO DE ISLR | E81: ISLR ANTICIPADO | K81: =+'GASTOS '!$J77*0.16 -> 0 | M81: =+'GASTOS '!$K77*'GASTOS '!$L77 -> 0 | O81: 745.64 | P81: =IFERROR( Tabla8[[#This Row],[PAGADO BS]]/Tabla8[[#This Row],[TASA DE CAMBIO]], 0) -> 1552.459 | Q81: 1157575.5 | R81: BANCOS | T81: 46233
A82: 79 | B82: 46233 | C82: SENIAT | D82: RETENCION DE IVA (COMPRAS) | E82: RETENCIÓN IVA | K82: =+'GASTOS '!$J78*0.16 -> 0 | M82: =+'GASTOS '!$K78*'GASTOS '!$L78 -> 0 | O82: 745.64 | P82: =IFERROR( Tabla8[[#This Row],[PAGADO BS]]/Tabla8[[#This Row],[TASA DE CAMBIO]], 0) -> 20271.091 | Q82: 15114936 | R82: BANCOS | T82: 46233
A83: 80 | B83: 46233 | C83: SENIAT | D83: DECLARACION DE IGTF | E83: IGTF | K83: =+'GASTOS '!$J79*0.16 -> 0 | M83: =+'GASTOS '!$K79*'GASTOS '!$L79 -> #REF! | O83: 745.64 | P83: =IFERROR( Tabla8[[#This Row],[PAGADO BS]]/Tabla8[[#This Row],[TASA DE CAMBIO]], 0) -> 507.81074 | Q83: 378644 | R83: BANCOS | T83: 46233
A84: 81 | B84: 46233 | C84: SENIAT | D84: DECLARACION DE PENSIONES IVSS JUNIO 2026 | E84: LEY DE PENSIONES | K84: =+'GASTOS '!$J80*0.16 -> 0 | M84: =+'GASTOS '!$K80*'GASTOS '!$L80 -> 0 | O84: 745.64 | P84: =IFERROR( Tabla8[[#This Row],[PAGADO BS]]/Tabla8[[#This Row],[TASA DE CAMBIO]], 0) -> 679.80615 | Q84: 506890.66 | R84: BANCOS | T84: 46233
A85: 82 | B85: 46233 | C85: CORPOELEC | D85: ELECTRICIDAD/RELLENO SANITARIO / TIENDA JULIO | E85: ELECTRICIDAD | K85: =+'GASTOS '!$J81*0.16 -> 0 | M85: =+'GASTOS '!$K81*'GASTOS '!$L81 -> 0 | O85: 745.64 | P85: =IFERROR( Tabla8[[#This Row],[PAGADO BS]]/Tabla8[[#This Row],[TASA DE CAMBIO]], 0) -> 77.511426 | Q85: 57795.62 | R85: BANCOS | T85: 46233
A86: 83 | B86: 46233 | C86: CORPOELEC | D86: ELECTRICIDAD/RELLENO SANITARIO / OFICINA | E86: ELECTRICIDAD | K86: =+'GASTOS '!$J82*0.16 -> 0 | M86: =+'GASTOS '!$K82*'GASTOS '!$L82 -> 0 | O86: 745.64 | P86: =IFERROR( Tabla8[[#This Row],[PAGADO BS]]/Tabla8[[#This Row],[TASA DE CAMBIO]], 0) -> 60.905263 | Q86: 45413.4 | R86: BANCOS | T86: 46233
A87: 84 | B87: 46233 | C87: COMPRAS | D87: DESENGRASANTE PARA JORNADA DE LAVADO EN TIENDA | E87: SERVICIO MTTO DE VEHICULOS | K87: =+'GASTOS '!$J83*0.16 -> 0 | M87: =+'GASTOS '!$K83*'GASTOS '!$L83 -> 0 | O87: 745.64 | P87: =IFERROR( Tabla8[[#This Row],[PAGADO BS]]/Tabla8[[#This Row],[TASA DE CAMBIO]], 0) -> 8 | Q87: 5965.12 | R87: BANCOS | T87: 46233
A88: 85 | B88: 46233 | C88: COMPRAS | D88: LAVADO DE PANEL | E88: SERVICIO MTTO DE VEHICULOS | K88: =+'GASTOS '!$J84*0.16 -> 0 | M88: =+'GASTOS '!$K84*'GASTOS '!$L84 -> 0 | O88: 745.64 | P88: =IFERROR( Tabla8[[#This Row],[PAGADO BS]]/Tabla8[[#This Row],[TASA DE CAMBIO]], 0) -> 25 | Q88: 18641 | R88: BANCOS | T88: 46233
A89: 86 | B89: 46233 | C89: TRABAJADORES | D89: NOMINA 2DA QNA JULIO | E89: NOMINA | K89: =+'GASTOS '!$J85*0.16 -> 0 | M89: =+'GASTOS '!$K85*'GASTOS '!$L85 -> 0 | O89: 745.64 | P89: =IFERROR( Tabla8[[#This Row],[PAGADO BS]]/Tabla8[[#This Row],[TASA DE CAMBIO]], 0) -> 195.95381 | Q89: 146111 | R89: BANCOS | T89: 46233
A90: 87 | B90: 46233 | C90: TRABAJADORES | D90: AYUDA SOCIAL DE TRANSPORTE | E90: AYUDA SOCIAL DE TRANSPORTE | K90: =+'GASTOS '!$J86*0.16 -> 0 | M90: =+'GASTOS '!$K86*'GASTOS '!$L86 -> 0 | O90: 745.64 | P90: =IFERROR( Tabla8[[#This Row],[PAGADO BS]]/Tabla8[[#This Row],[TASA DE CAMBIO]], 0) -> 3136.7156 | Q90: 2338860.6 | R90: BANCOS | T90: 46233
A91: 88 | B91: 46234 | C91: TRABAJADORES | D91: LIQUIDACION ( Edil Gil / Franklin Van Der) | E91: LIQUIDACIONES (PERSONAL) | K91: =+'GASTOS '!$J87*0.16 -> 0 | M91: =+'GASTOS '!$K87*'GASTOS '!$L87 -> 0 | O91: 746.63 | P91: =IFERROR( Tabla8[[#This Row],[PAGADO BS]]/Tabla8[[#This Row],[TASA DE CAMBIO]], 0) -> 171.66785 | Q91: 128172.37 | R91: BANCOS | T91: 46234
A92: 89 | B92: 46234 | C92: INCES | D92: 0,5% POR APORTE DE LIQUIDACIONES DE PRESTACIONES SOCIALES | E92: INCES | K92: =+'GASTOS '!$J88*0.16 -> 0 | M92: =+'GASTOS '!$K88*'GASTOS '!$L88 -> 0 | O92: 746.63 | P92: =IFERROR( Tabla8[[#This Row],[PAGADO BS]]/Tabla8[[#This Row],[TASA DE CAMBIO]], 0) -> 0.14286862 | Q92: 106.67 | R92: BANCOS | T92: 46234
A93: 90 | K93: =+'GASTOS '!$J89*0.16 -> 0 | M93: =+'GASTOS '!$K89*'GASTOS '!$L89 -> 0 | P93: =IFERROR( Tabla8[[#This Row],[PAGADO BS]]/Tabla8[[#This Row],[TASA DE CAMBIO]], 0) -> 0
K94: =+'GASTOS '!$J90*0.16 -> 0 | M94: =+'GASTOS '!$K90*'GASTOS '!$L90 -> 0
K95: =+'GASTOS '!$J95*0.16 -> 0 | M95: =+'GASTOS '!$K95*'GASTOS '!$L95 -> 0 | P95: =IFERROR( Tabla8[[#This Row],[PAGADO BS]]/Tabla8[[#This Row],[TASA DE CAMBIO]], 0) -> 0
K96: =+'GASTOS '!$J96*0.16 -> 0 | M96: =+'GASTOS '!$K96*'GASTOS '!$L96 -> 0 | P96: =IFERROR( Tabla8[[#This Row],[PAGADO BS]]/Tabla8[[#This Row],[TASA DE CAMBIO]], 0) -> 0
K97: =+'GASTOS '!$J97*0.16 -> 0 | M97: =+'GASTOS '!$K97*'GASTOS '!$L97 -> 0 | P97: =IFERROR( Tabla8[[#This Row],[PAGADO BS]]/Tabla8[[#This Row],[TASA DE CAMBIO]], 0) -> 0
K98: =+'GASTOS '!$J98*0.16 -> 0 | M98: =+'GASTOS '!$K98*'GASTOS '!$L98 -> 0 | P98: =IFERROR( Tabla8[[#This Row],[PAGADO BS]]/Tabla8[[#This Row],[TASA DE CAMBIO]], 0) -> 0
K99: =+'GASTOS '!$J99*0.16 -> 0 | M99: =+'GASTOS '!$K99*'GASTOS '!$L99 -> 0 | P99: =IFERROR( Tabla8[[#This Row],[PAGADO BS]]/Tabla8[[#This Row],[TASA DE CAMBIO]], 0) -> 0
K100: =+'GASTOS '!$J100*0.16 -> 0 | M100: =+'GASTOS '!$K100*'GASTOS '!$L100 -> 0 | P100: =IFERROR( Tabla8[[#This Row],[PAGADO BS]]/Tabla8[[#This Row],[TASA DE CAMBIO]], 0) -> 0
K101: =+'GASTOS '!$J101*0.16 -> 0 | M101: =+'GASTOS '!$K101*'GASTOS '!$L101 -> 0 | P101: =IFERROR( Tabla8[[#This Row],[PAGADO BS]]/Tabla8[[#This Row],[TASA DE CAMBIO]], 0) -> 0
...

Sheet FONDO EN CAJA $ BS
D1: Global IT System, C.A | M1: Global IT System, C.A | V1: Global IT System, C.A
D2: J-40685449-2 | M2: J-40685449-2 | V2: J-40685449-2
D4: MES: | E4: JULIO | M4: MES: | N4: JULIO | V4: MES: | W4: Julio
D5: CAJA: | E5: 1 / RODERICK | M5: CAJA: | N5: 2 / WENDY | V5: INICIO: | W5: 600
C7: EFECTIVO BS | L7: EFECTIVO BS | U7: EFECTIVO BS
C10: INGRESOS | L10: INGRESOS | U10: INGRESOS
C12: FECHA | D12: APERTURA | E12: FACTURA | F12: N/E | G12: OTROS | H12: SALDO EN CAJA | I12: CAJA GERENCIA | J12: SALDO FINAL | L12: FECHA | M12: APERTURA | N12: FACTURA | O12: N/E | P12: OTROS | Q12: SALDO EN CAJA | R12: ENVIADO A GERENCIA | S12: SALDO FINAL | U12: FECHA | V12: INGRESOS | W12: EGRESOS | X12: TOTAL | Y12: TOTAL | Z12: T/C
C13: 46204 | D13: 463 | E13: 0 | F13: 5219 | G13: 0 | H13: =+D13+E13+F13+G13 -> 5682 | I13: 5200 | J13: =+H13-I13 -> 482 | L13: 46204 | M13: 582 | N13: 0 | O13: 2894 | P13: 0 | Q13: =+M13+N13+O13+P13 -> 3476 | R13: 3100 | S13: =+Q13-R13 -> 376 | U13: 46204 | V13: 19100 | W13: =100+100+100+1800+2300 -> 4400 | X13: =V13+W5-W13 -> 15300 | Y13: =X13/Z13 -> 24.156878 | Z13: 633.36
C14: 46205 | D14: 482 | E14: 0 | F14: 3167 | G14: 0 | H14: =+D14+E14+F14+G14 -> 3649 | I14: 3200 | J14: =H14-I14 -> 449 | L14: 46205 | M14: 376 | N14: 200 | O14: 715 | P14: 0 | Q14: =SUM(M14:P14) -> 1291 | R14: 900 | S14: =+Q14-R14 -> 391 | U14: 46205 | V14: =700+400 -> 1100 | W14: =300+500+400+100 -> 1300 | X14: =V14+X13-W14 -> 15100 | Y14: =X14/Z14 -> 23.604815 | Z14: 639.7
C15: 46206 | D15: 449 | E15: 0 | F15: 517 | G15: 0 | H15: =+D15+E15+F15+G15 -> 966 | I15: 500 | J15: =H15-I15 -> 466 | L15: 46206 | M15: 391 | N15: 20 | O15: 1365 | P15: 0 | Q15: =SUM(M15:P15) -> 1776 | R15: 1300 | S15: =+Q15-R15 -> 476 | U15: 46206 | V15: 300 | W15: =100+400+1200+1800+1700+900 -> 6100 | X15: =V15+X14-W15 -> 9300 | Y15: =X15/Z15 -> 14.242615 | Z15: 652.97
C16: 46209 | D16: 466 | E16: 5 | F16: 599 | G16: 0 | H16: =+D16+E16+F16+G16 -> 1070 | I16: 600 | J16: =H16-I16 -> 470 | L16: 46209 | M16: 476 | N16: 0 | O16: 2280 | P16: 0 | Q16: =SUM(M16:P16) -> 2756 | R16: 2200 | S16: =+Q16-R16 -> 556 | U16: 46209 | V16: 36000 | W16: =200+600+1000+1000+3500+1000+500 -> 7800 | X16: =V16+X15-W16 -> 37500 | Y16: =X16/Z16 -> 56.217675 | Z16: 667.05
C17: 46210 | D17: 470 | E17: 30 | F17: 1428 | G17: 0 | H17: =+D17+E17+F17+G17 -> 1928 | I17: 1500 | J17: =H17-I17 -> 428 | L17: 46210 | M17: 556 | N17: 0 | O17: 2230 | P17: 0 | Q17: =SUM(M17:P17) -> 2786 | R17: 2400 | S17: =+Q17-R17 -> 386 | U17: 46210 | V17: 0 | W17: =1500+500+1000+1000+3000 -> 7000 | X17: =V17+X16-W17 -> 30500 | Y17: =X17/Z17 -> 45.189872 | Z17: 674.93
C18: 46211 | D18: 428 | E18: 0 | F18: 452 | G18: 0 | H18: =+D18+E18+F18+G18 -> 880 | I18: 400 | J18: =H18-I18 -> 480 | L18: 46211 | M18: 386 | N18: 0 | O18: 895 | P18: 0 | Q18: =SUM(M18:P18) -> 1281 | R18: 1000 | S18: =+Q18-R18 -> 281 | U18: 46211 | V18: 0 | W18: =500+500+500+500+500 -> 2500 | X18: =V18+X17-W18 -> 28000 | Y18: =X18/Z18 -> 40.819897 | Z18: 685.94
C19: 46212 | D19: 480 | E19: 0 | F19: 595 | G19: 0 | H19: =+D19+E19+F19+G19 -> 1075 | I19: 600 | J19: =H19-I19 -> 475 | L19: 46212 | M19: 281 | N19: 0 | O19: 584 | P19: 286 | Q19: =SUM(M19:P19) -> 1151 | R19: 850 | S19: =+Q19-R19 -> 301 | U19: 46212 | V19: 3250 | W19: =2000+100+650+2100+700 -> 5550 | X19: =V19+X18-W19 -> 25700 | Y19: =X19/Z19 -> 36.702751 | Z19: 700.22
C20: 46213 | D20: 475 | E20: 0 | F20: 101 | G20: 0 | H20: =+D20+E20+F20+G20 -> 576 | I20: 200 | J20: =H20-I20 -> 376 | L20: 46213 | M20: 301 | N20: 0 | O20: 1405 | P20: 0 | Q20: =SUM(M20:P20) -> 1706 | R20: 1400 | S20: =+Q20-R20 -> 306 | U20: 46213 | V20: 0 | W20: =500+1500 -> 2000 | X20: =V20+X19-W20 -> 23700 | Y20: =X20/Z20 -> 33.394863 | Z20: 709.69
C21: 46216 | D21: 376 | E21: 41 | F21: 1074.6 | G21: 170 | H21: =+D21+E21+F21+G21 -> 1661.6 | I21: 1408.6 | J21: =H21-I21 -> 253 | L21: 46216 | M21: 306 | N21: 0 | O21: 654 | P21: 0 | Q21: =SUM(M21:P21) -> 960 | R21: 650 | S21: =+Q21-R21 -> 310 | U21: 46216 | V21: 0 | W21: =900+400+250 -> 1550 | X21: =V21+X20-W21 -> 22150 | Y21: =X21/Z21 -> 30.706315 | Z21: 721.35
C22: 46217 | D22: 253 | E22: 0 | F22: 1513 | G22: 0 | H22: =+D22+E22+F22+G22 -> 1766 | I22: 1400 | J22: =H22-I22 -> 366 | L22: 46217 | M22: 310 | N22: 0 | O22: 1075 | P22: 0 | Q22: =SUM(M22:P22) -> 1385 | R22: 1000 | S22: =+Q22-R22 -> 385 | U22: 46217 | V22: 0 | W22: =500+350+100+2200+1100+1200+100+500+1700 -> 7750 | X22: =V22+X21-W22 -> 14400 | Y22: =X22/Z22 -> 19.889503 | Z22: 724
C23: 46218 | D23: 366 | E23: 0 | F23: 1010 | G23: 0 | H23: =+D23+E23+F23+G23 -> 1376 | I23: 900 | J23: =H23-I23 -> 476 | L23: 46218 | M23: 385 | N23: 0 | O23: 655 | P23: 0 | Q23: =SUM(M23:P23) -> 1040 | R23: 700 | S23: =+Q23-R23 -> 340 | U23: 46218 | V23: 0 | W23: =600+200+500+500+1500+500+600+3000 -> 7400 | X23: =V23+X22-W23 -> 7000 | Y23: =X23/Z23 -> 9.6451946 | Z23: 725.75
C24: 46219 | D24: 476 | E24: 0 | F24: 5835 | G24: 0 | H24: =+D24+E24+F24+G24 -> 6311 | I24: 5800 | J24: =H24-I24 -> 511 | L24: 46219 | M24: 340 | N24: 50 | O24: 1499 | P24: 0 | Q24: =SUM(M24:P24) -> 1889 | R24: 1550 | S24: =+Q24-R24 -> 339 | U24: 46219 | V24: 0 | W24: =1500+500+1000+2000+500+1500 -> 7000 | X24: =V24+X23-W24 -> 0 | Y24: =X24/Z24 -> 0 | Z24: 727.45
C25: 46220 | D25: 511 | E25: 50 | F25: 2519 | G25: 0 | H25: =+D25+E25+F25+G25 -> 3080 | I25: 2600 | J25: =H25-I25 -> 480 | L25: 46220 | M25: 339 | N25: 0 | O25: 442 | P25: 0 | Q25: =SUM(M25:P25) -> 781 | R25: 400 | S25: =+Q25-R25 -> 381 | U25: 46220 | V25: 7050 | W25: =500+1700+1200+400+100 -> 3900 | X25: =V25+X24-W25 -> 3150 | Y25: =X25/Z25 -> 4.3301945 | Z25: 727.45
C26: 46223 | D26: 480 | E26: 0 | F26: 1349 | G26: 0 | H26: =+D26+E26+F26+G26 -> 1829 | I26: 1400 | J26: =H26-I26 -> 429 | L26: 46223 | M26: 381 | N26: 0 | O26: 1276 | P26: 0 | Q26: =SUM(M26:P26) -> 1657 | R26: 1200 | S26: =+Q26-R26 -> 457 | U26: 46223 | V26: 350 | W26: =500+450+500+350 -> 1800 | X26: =V26-W26+X25 -> 1700 | Y26: =X26/Z26 -> 2.3068677 | Z26: 736.93
C27: 46224 | D27: 429 | E27: 52 | F27: 2025 | G27: 40 | H27: =+D27+E27+F27+G27 -> 2546 | I27: 2000 | J27: =H27-I27 -> 546 | L27: 46224 | M27: 457 | N27: 0 | O27: 993 | P27: 0 | Q27: =SUM(M27:P27) -> 1450 | R27: 1000 | S27: =+Q27-R27 -> 450 | U27: 46224 | V27: 500 | W27: =1050+300+700+150 -> 2200 | X27: =V27-W27+X26 -> 0 | Y27: =X27/Z27 -> 0 | Z27: 737.23
C28: 46225 | D28: 546 | E28: 0 | F28: 1321 | G28: 0 | H28: =+D28+E28+F28+G28 -> 1867 | I28: 1300 | J28: =H28-I28 -> 567 | L28: 46225 | M28: 450 | N28: 0 | O28: 1180 | P28: 0 | Q28: =SUM(M28:P28) -> 1630 | R28: 1300 | S28: =+Q28-R28 -> 330 | U28: 46226 | V28: 170 | W28: 0 | X28: =V28+X27-W28 -> 170 | Y28: =X28/Z28 -> 0.23038977 | Z28: 737.88
C29: 46226 | D29: 567 | E29: 0 | F29: 229 | G29: 2000 | H29: =+D29+E29+F29+G29 -> 2796 | I29: 2300 | J29: =H29-I29 -> 496 | L29: 46226 | M29: 330 | N29: 230 | O29: 494 | P29: 0 | Q29: =SUM(M29:P29) -> 1054 | R29: 700 | S29: =+Q29-R29 -> 354 | U29: 46230 | V29: =750+200 -> 950 | W29: 170 | X29: =V29+X28-W29 -> 950 | Y29: =X29/Z29 -> 1.2799267 | Z29: 742.23
C30: 46227 | D30: 496 | E30: 0 | F30: 526 | G30: 0 | H30: =+D30+E30+F30+G30 -> 1022 | I30: 600 | J30: =H30-I30 -> 422 | L30: 46230 | M30: 354 | N30: 93 | O30: 1883 | P30: 500 | Q30: =SUM(M30:P30) -> 2830 | R30: 2350 | S30: =+Q30-R30 -> 480 | U30: 46231 | V30: =11900+370 -> 12270 | W30: =850+100 -> 950 | X30: =V30+X29-W30 -> 12270 | Y30: =X30/Z30 -> 16.518356 | Z30: 742.81
C31: 46230 | D31: 422 | E31: 0 | F31: 945 | G31: 0 | H31: =+D31+E31+F31+G31 -> 1367 | I31: 1100 | J31: =H31-I31 -> 267 | L31: 46231 | M31: 480 | N31: 0 | O31: 1667 | P31: 84 | Q31: =SUM(M31:P31) -> 2231 | R31: 1800 | S31: =+Q31-R31 -> 431 | U31: 46232 | V31: 100 | W31: =560+2050+160+200+200 -> 3170 | X31: =V31+X30-W31 -> 9200 | Y31: =X31/Z31 -> 12.361936 | Z31: 744.22
C32: 46231 | D32: 267 | E32: 0 | F32: 705 | G32: 0 | H32: =+D32+E32+F32+G32 -> 972 | I32: 500 | J32: =H32-I32 -> 472 | L32: 46232 | M32: 431 | N32: 0 | O32: 1349 | P32: 0 | Q32: =SUM(M32:P32) -> 1780 | R32: 1200 | S32: =+Q32-R32 -> 580 | U32: 46233 | V32: 0 | W32: =600+400+2000+1200+2000+2000 -> 8200 | X32: =V32+X31-W32 -> 1000 | Y32: =X32/Z32 -> 1.3411298 | Z32: 745.64
C33: 46232 | D33: 472 | E33: 70 | F33: 767 | G33: 781.01 | H33: =+D33+E33+F33+G33 -> 2090.01 | I33: 1681.01 | J33: =H33-I33 -> 409 | L33: 46233 | M33: 580 | N33: 0 | O33: 1560 | P33: 3000 | Q33: =SUM(M33:P33) -> 5140 | R33: 4700 | S33: =+Q33-R33 -> 440 | U33: 46234 | V33: 1000 | W33: =120+200+600 -> 920 | X33: =V33+X32-W33 -> 1080 | Y33: =X33/Z33 -> 1.4464996 | Z33: 746.63
C34: 46233 | D34: 409 | E34: 20 | F34: 233 | G34: 0 | H34: =+D34+E34+F34+G34 -> 662 | I34: 300 | J34: =H34-I34 -> 362 | L34: 46234 | M34: 440 | N34: 0 | O34: 2231 | P34: 0 | Q34: =SUM(M34:P34) -> 2671 | R34: 2400 | S34: =+Q34-R34 -> 271 | V34: 0 | W34: 0 | X34: 0 | Y34: 0 | Z34: 0
C35: 46234 | D35: 362 | E35: 0 | F35: 734 | G35: 0 | H35: =+D35+E35+F35+G35 -> 1096 | I35: 900 | J35: =H35-I35 -> 196 | M35: 0 | N35: 0 | O35: 0 | P35: 0 | Q35: =SUM(M35:P35) -> 0 | R35: 0 | S35: =+Q35-R35 -> 0 | V35: 0 | W35: 0 | X35: =V35+X34-W35 -> 0 | Y35: 0 | Z35: 0
C36: TOTAL | I36: =SUM(I13:I35) -> 36389.61 | L36: TOTAL | R36: =SUM(R13:R35) -> 34100
U37: TOTAL CIERRE EN EFECTIVO BS | Y37: 1080
C38: OBSERVACIONES: | U38: TOTAL BS AL CAMBIO. | Y38: =+Y33 -> 1.4464996
C42: Jefe de caja:
C46: Coord. De Administración

Sheet CAJA ADM
C2: CONTROL DE CAJA ADMINISTRACIÓN
D3: INGRESOS | F3: SALIDAS | G3: SALDOS FINALES
D4: USD | F4: USD
A5: NRO DE RECIBO | B5: FECHA | C5: DESCRIPCION | D5: INGRESOS | E5: VUELTOS | F5: EGRESOS EN CAJA | G5: APARTADO | H5: USD TOTAL
B6: 46204 | C6: SALDO DE APERTURA | D6: =+'[2]CAJA ADMON JUN'!H15 -> 270 | E6: 0 | F6: 0 | G6: 0 | H6: =IFERROR(+D6+E6-F6-G6,"0") -> 270
A7: 00-0101 | B7: 46205 | C7: GASTOS DE SEGURIDAD | D7: =+'[2]CAJA ADMON JUN'!H16 -> 0 | F7: 50 | H7: =IFERROR(+D7+E7-F7-G7,"0") -> -50
A8: 00-0102 | B8: 46212 | C8: GASTOS DE SEGURIDAD | D8: =+'[2]CAJA ADMON JUN'!H17 -> 0 | F8: 50 | H8: =IFERROR(+D8+E8-F8-G8,"0") -> -50
A9: 00-0103 | B9: 46212 | C9: PAGO ALQUILER ESTACIONAMIENTO DE TIENDA | D9: =+'[2]CAJA ADMON JUN'!H18 -> 0 | F9: 90 | H9: =IFERROR(+D9+E9-F9-G9,"0") -> -90
A10: 00-0104 | B10: 46219 | C10: GASTOS DE SEGURIDAD | D10: =+'[2]CAJA ADMON JUN'!H19 -> 0 | F10: 50 | H10: =IFERROR(+D10+E10-F10-G10,"0") -> -50
A11: INGRESO | B11: 46226 | C11: REPOSICION FONDO DE CAJA | D11: 500 | H11: =IFERROR(+D11+E11-F11-G11,"0") -> 500
A12: 00-0105 | B12: 46226 | C12: GASTOS DE SEGURIDAD | D12: 0 | F12: 50 | H12: =IFERROR(+D12+E12-F12-G12,"0") -> -50
A13: 00-0106 | B13: 46233 | C13: GASTOS DE SEGURIDAD | D13: 0 | F13: 50 | H13: =IFERROR(+D13+E13-F13-G13,"0") -> -50
A14: 00-0107 | D14: 0 | H14: =IFERROR(+D14+E14-F14-G14,"0") -> 0
A15: 00-0108 | D15: =+'[2]CAJA ADMON JUN'!H23 -> 0 | H15: =IFERROR(+D15+E15-F15-G15,"0") -> 0
H16: =SUBTOTAL(109,H6:H15) -> 30
A17: Se finaliza el presente arqueo de caja con un total de USD ______________________________, pasando a
A18: firmar en señal de conformidad. | D18: Denominación | E18: cantidad | F18: total efectivo | G18: DIFERENCIA | H18: =E24-H16 -> 400
D19: 5 | E19: 0 | F19: =+D19*E19 -> 0
D20: 10 | E20: 0 | F20: =+D20*E20 -> 0
D21: 20 | E21: 9 | F21: =+D21*E21 -> 180
A22: Encargado de Caja / Desembolsos | D22: 50 | E22: 5 | F22: =+D22*E22 -> 250 | G22: FALTANTE | H22: =IF($H$18<0,"x","")
D23: 100 | E23: 0 | F23: =+D23*E23 -> 0 | G23: SOBRANTE | H23: =IF($H$18>0,"x","") -> x
D24: TOTAL | E24: =SUM(F19:F23) -> 430
A27: Supervisor/ Administracion

Sheet COMPARAT
A6: MES | B6: ENTRADA Z
A7: ENERO
A8: FEBRERO
A9: MARZO
A10: ABRIL
A11: MAYO
A12: JUNIO
A13: JULIO
A14: AGOSTO
A15: SEPTIEMBRE
A16: OCTUBRE
A17: NOVIEMBRE
A18: DICIEMBRE

Sheet COMPARAT COMPRAS

Sheet T.D COMPRAS
A3: Suma de USD
A4: TIPO DE COMPRA | B4: Total
A5: (en blanco) | B5: 0
A6: REPOSICION DE MERCANCIA | B6: 227987.17
A7: PAGO 25% IVA | B7: 10524.504
A8: Total general | B8: 238511.68

Sheet T.D GASTOS
A1: FECHA | B1: (Todas)
A3: Suma de USD
A4: TIPO DE GASTOS | B4: Total
A5: ALQUILERES | B5: 2289.2339
A6: BONO ALIMENTACION | B6: 1518.7244
A7: CANTV | B7: 31.978726
A8: COMPLEMENTO BONO ALIMENTACION | B8: 4563.0579
A9: DIGITEL | B9: 125.60974
A10: HIDROCAPITAL | B10: 104.61625
A11: IAE (ALCALDIA) | B11: 6418.4906
A12: IGTF | B12: 508.33475
A13: INCES | B13: 27.35732
A14: INTERNET | B14: 388.53532
A15: ISLR ANTICIPADO | B15: 2430.8674
A16: IVSS | B16: 7.1511463
... A48: Total general | B48: 81702.98
